{
  "timestamp": "2025-08-22T15:16:58.524Z",
  "athleteName": "Stephanie Kennedy",
  "totalCompetitions": 13,
  "analysis": {
    "distinctAthletes": 2,
    "membershipGroups": {
      "217283": [
        {
          "meet_id": 2951,
          "date": "2018-03-18",
          "age_category": "Open Women's",
          "weight_class": "90 kg",
          "lifter_name": "Stephanie Kennedy",
          "lifter_id": 34516,
          "membershipNumbers": [
            {
              "athleteName": "Stephanie Kennedy",
              "membershipNumber": "217283",
              "fullText": "4  -  131  Stephanie Kennedy  F  34  LEHIGH VALLEY BARBELL CLUB  217283  79.75  2018-03-18  -  Local  Pennsylvania-West Virginia"
            }
          ],
          "sport80Url": "https://usaweightlifting.sport80.com/public/rankings/all?filters=eyJkYXRlX3JhbmdlX3N0YXJ0IjoiMjAxOC0wMy0xOCIsImRhdGVfcmFuZ2VfZW5kIjoiMjAxOC0wMy0xOCIsIndlaWdodF9jbGFzcyI6MzY5fQ=="
        }
      ],
      "1064080": [
        {
          "meet_id": 5717,
          "date": "2023-02-11",
          "age_category": "Open Women's",
          "weight_class": "55kg",
          "lifter_name": "Stephanie Kennedy",
          "lifter_id": 34516,
          "membershipNumbers": [
            {
              "athleteName": "Stephanie Kennedy",
              "membershipNumber": "1064080",
              "fullText": "3  -  142  Stephanie Kennedy  F  31  Greenville Weightlifting  1064080  52.65  2023-02-11  -  Local  Carolina"
            }
          ],
          "sport80Url": "https://usaweightlifting.sport80.com/public/rankings/all?filters=eyJkYXRlX3JhbmdlX3N0YXJ0IjoiMjAyMy0wMi0xMSIsImRhdGVfcmFuZ2VfZW5kIjoiMjAyMy0wMi0xMSIsIndlaWdodF9jbGFzcyI6OTN9"
        },
        {
          "meet_id": 5999,
          "date": "2023-08-12",
          "age_category": "Open Women's",
          "weight_class": "55kg",
          "lifter_name": "Stephanie Kennedy",
          "lifter_id": 34516,
          "membershipNumbers": [
            {
              "athleteName": "Stephanie Kennedy",
              "membershipNumber": "1064080",
              "fullText": "2  -  153  Stephanie Kennedy  F  31  Greenville Weightlifting  1064080  54.4  2023-08-12  -  Local  Carolina"
            }
          ],
          "sport80Url": "https://usaweightlifting.sport80.com/public/rankings/all?filters=eyJkYXRlX3JhbmdlX3N0YXJ0IjoiMjAyMy0wOC0xMiIsImRhdGVfcmFuZ2VfZW5kIjoiMjAyMy0wOC0xMiIsIndlaWdodF9jbGFzcyI6OTN9"
        },
        {
          "meet_id": 6172,
          "date": "2023-12-07",
          "age_category": "Open Women's",
          "weight_class": "55kg",
          "lifter_name": "Stephanie Kennedy",
          "lifter_id": 34516,
          "membershipNumbers": [
            {
              "athleteName": "Stephanie Kennedy",
              "membershipNumber": "1064080",
              "fullText": "13  -  149  Stephanie Kennedy  F  31  Greenville Weightlifting  1064080  53.52  2023-12-07  -  North American Open Series  Carolina"
            }
          ],
          "sport80Url": "https://usaweightlifting.sport80.com/public/rankings/all?filters=eyJkYXRlX3JhbmdlX3N0YXJ0IjoiMjAyMy0xMi0wNyIsImRhdGVfcmFuZ2VfZW5kIjoiMjAyMy0xMi0wNyIsIndlaWdodF9jbGFzcyI6OTN9"
        },
        {
          "meet_id": 5869,
          "date": "2023-04-22",
          "age_category": "Open Women's",
          "weight_class": "55kg",
          "lifter_name": "Stephanie Kennedy",
          "lifter_id": 34516,
          "membershipNumbers": [
            {
              "athleteName": "Stephanie Kennedy",
              "membershipNumber": "1064080",
              "fullText": "2  -  141  Stephanie Kennedy  F  31  Greenville Weightlifting  1064080  53.6  2023-04-22  -  Local  Carolina"
            }
          ],
          "sport80Url": "https://usaweightlifting.sport80.com/public/rankings/all?filters=eyJkYXRlX3JhbmdlX3N0YXJ0IjoiMjAyMy0wNC0yMiIsImRhdGVfcmFuZ2VfZW5kIjoiMjAyMy0wNC0yMiIsIndlaWdodF9jbGFzcyI6OTN9"
        },
        {
          "meet_id": 6244,
          "date": "2024-02-11",
          "age_category": "Open Women's",
          "weight_class": "55kg",
          "lifter_name": "Stephanie Kennedy",
          "lifter_id": 34516,
          "membershipNumbers": [
            {
              "athleteName": "Stephanie Kennedy",
              "membershipNumber": "1064080",
              "fullText": "2  -  150  Stephanie Kennedy  F  32  Greenville Weightlifting  1064080  54.05  2024-02-11  -  Local  Carolina"
            }
          ],
          "sport80Url": "https://usaweightlifting.sport80.com/public/rankings/all?filters=eyJkYXRlX3JhbmdlX3N0YXJ0IjoiMjAyNC0wMi0xMSIsImRhdGVfcmFuZ2VfZW5kIjoiMjAyNC0wMi0xMSIsIndlaWdodF9jbGFzcyI6OTN9"
        },
        {
          "meet_id": 6506,
          "date": "2024-08-24",
          "age_category": "Open Women's",
          "weight_class": "55kg",
          "lifter_name": "Stephanie Kennedy",
          "lifter_id": 34516,
          "membershipNumbers": [
            {
              "athleteName": "Stephanie Kennedy",
              "membershipNumber": "1064080",
              "fullText": "1  -  153  Stephanie Kennedy  F  32  Greenville Weightlifting  1064080  54.85  2024-08-24  -  Local  Carolina"
            }
          ],
          "sport80Url": "https://usaweightlifting.sport80.com/public/rankings/all?filters=eyJkYXRlX3JhbmdlX3N0YXJ0IjoiMjAyNC0wOC0yNCIsImRhdGVfcmFuZ2VfZW5kIjoiMjAyNC0wOC0yNCIsIndlaWdodF9jbGFzcyI6OTN9"
        },
        {
          "meet_id": 6778,
          "date": "2025-02-27",
          "age_category": "Open Women's",
          "weight_class": "59kg",
          "lifter_name": "Stephanie Kennedy",
          "lifter_id": 34516,
          "membershipNumbers": [
            {
              "athleteName": "Stephanie Kennedy",
              "membershipNumber": "1064080",
              "fullText": "15  -  154  Stephanie Kennedy  F  33  Greenville Weightlifting  1064080  56.07  2025-02-27  -  North American Open Series  Carolina"
            }
          ],
          "sport80Url": "https://usaweightlifting.sport80.com/public/rankings/all?filters=eyJkYXRlX3JhbmdlX3N0YXJ0IjoiMjAyNS0wMi0yNyIsImRhdGVfcmFuZ2VfZW5kIjoiMjAyNS0wMi0yNyIsIndlaWdodF9jbGFzcyI6OTR9"
        },
        {
          "meet_id": 5478,
          "date": "2022-08-27",
          "age_category": "Open Women's",
          "weight_class": "55kg",
          "lifter_name": "Stephanie Kennedy",
          "lifter_id": 34516,
          "membershipNumbers": [
            {
              "athleteName": "Stephanie Kennedy",
              "membershipNumber": "1064080",
              "fullText": "1  -  144  Stephanie Kennedy  F  30  Greenville Weightlifting  1064080  51.85  2022-08-27  -  Local  Carolina"
            }
          ],
          "sport80Url": "https://usaweightlifting.sport80.com/public/rankings/all?filters=eyJkYXRlX3JhbmdlX3N0YXJ0IjoiMjAyMi0wOC0yNyIsImRhdGVfcmFuZ2VfZW5kIjoiMjAyMi0wOC0yNyIsIndlaWdodF9jbGFzcyI6OTN9"
        },
        {
          "meet_id": 6950,
          "date": "2025-06-27",
          "age_category": "Open Women's",
          "weight_class": "58kg",
          "lifter_name": "Stephanie Kennedy",
          "lifter_id": 34516,
          "membershipNumbers": [
            {
              "athleteName": "Stephanie Kennedy",
              "membershipNumber": "1064080",
              "fullText": "13  -  158  Stephanie Kennedy  F  33  Greenville Weightlifting  1064080  56.65  2025-06-27  -  National  Carolina"
            }
          ],
          "sport80Url": "https://usaweightlifting.sport80.com/public/rankings/all?filters=eyJkYXRlX3JhbmdlX3N0YXJ0IjoiMjAyNS0wNi0yNyIsImRhdGVfcmFuZ2VfZW5kIjoiMjAyNS0wNi0yNyIsIndlaWdodF9jbGFzcyI6NzA3fQ=="
        },
        {
          "meet_id": 6582,
          "date": "2024-10-19",
          "age_category": "Open Women's",
          "weight_class": "59kg",
          "lifter_name": "Stephanie Kennedy",
          "lifter_id": 34516,
          "membershipNumbers": [
            {
              "athleteName": "Stephanie Kennedy",
              "membershipNumber": "1064080",
              "fullText": "2  -  150  Stephanie Kennedy  F  32  Greenville Weightlifting  1064080  56.7  2024-10-19  -  Local  Carolina"
            }
          ],
          "sport80Url": "https://usaweightlifting.sport80.com/public/rankings/all?filters=eyJkYXRlX3JhbmdlX3N0YXJ0IjoiMjAyNC0xMC0xOSIsImRhdGVfcmFuZ2VfZW5kIjoiMjAyNC0xMC0xOSIsIndlaWdodF9jbGFzcyI6OTR9"
        },
        {
          "meet_id": 6044,
          "date": "2023-10-14",
          "age_category": "Open Women's",
          "weight_class": "55kg",
          "lifter_name": "Stephanie Kennedy",
          "lifter_id": 34516,
          "membershipNumbers": [
            {
              "athleteName": "Stephanie Kennedy",
              "membershipNumber": "1064080",
              "fullText": "1  -  152  Stephanie Kennedy  F  31  Greenville Weightlifting  1064080  53.65  2023-10-14  -  Local  Carolina"
            }
          ],
          "sport80Url": "https://usaweightlifting.sport80.com/public/rankings/all?filters=eyJkYXRlX3JhbmdlX3N0YXJ0IjoiMjAyMy0xMC0xNCIsImRhdGVfcmFuZ2VfZW5kIjoiMjAyMy0xMC0xNCIsIndlaWdodF9jbGFzcyI6OTN9"
        }
      ]
    },
    "unidentifiedCompetitions": [
      {
        "meet_id": 5785,
        "date": "2023-04-01",
        "age_category": "Open Women's",
        "weight_class": "55kg",
        "lifter_name": "Stephanie Kennedy",
        "lifter_id": 34516,
        "membershipNumbers": [],
        "sport80Url": "https://usaweightlifting.sport80.com/public/rankings/all?filters=eyJkYXRlX3JhbmdlX3N0YXJ0IjoiMjAyMy0wNC0wMSIsImRhdGVfcmFuZ2VfZW5kIjoiMjAyMy0wNC0wMSIsIndlaWdodF9jbGFzcyI6OTN9"
      }
    ],
    "splitRequired": true
  },
  "splitPlan": {
    "action": "SPLIT_REQUIRED",
    "originalAthleteName": "Stephanie Kennedy",
    "splits": [
      {
        "newAthleteName": "Stephanie Kennedy (Person 1)",
        "membershipNumber": "217283",
        "competitionCount": 1,
        "competitions": [
          2951
        ]
      },
      {
        "newAthleteName": "Stephanie Kennedy (Person 2)",
        "membershipNumber": "1064080",
        "competitionCount": 11,
        "competitions": [
          5717,
          5999,
          6172,
          5869,
          6244,
          6506,
          6778,
          5478,
          6950,
          6582,
          6044
        ]
      }
    ],
    "unidentifiedCompetitions": [
      {
        "meet_id": 5785,
        "date": "2023-04-01",
        "age_category": "Open Women's",
        "weight_class": "55kg",
        "lifter_name": "Stephanie Kennedy",
        "lifter_id": 34516,
        "membershipNumbers": [],
        "sport80Url": "https://usaweightlifting.sport80.com/public/rankings/all?filters=eyJkYXRlX3JhbmdlX3N0YXJ0IjoiMjAyMy0wNC0wMSIsImRhdGVfcmFuZ2VfZW5kIjoiMjAyMy0wNC0wMSIsIndlaWdodF9jbGFzcyI6OTN9"
      }
    ]
  },
  "rawData": {
    "athleteName": "Stephanie Kennedy",
    "competitions": [
      {
        "meet_id": 5785,
        "date": "2023-04-01",
        "age_category": "Open Women's",
        "weight_class": "55kg",
        "lifter_name": "Stephanie Kennedy",
        "lifter_id": 34516,
        "membershipNumbers": [],
        "sport80Url": "https://usaweightlifting.sport80.com/public/rankings/all?filters=eyJkYXRlX3JhbmdlX3N0YXJ0IjoiMjAyMy0wNC0wMSIsImRhdGVfcmFuZ2VfZW5kIjoiMjAyMy0wNC0wMSIsIndlaWdodF9jbGFzcyI6OTN9"
      },
      {
        "meet_id": 5717,
        "date": "2023-02-11",
        "age_category": "Open Women's",
        "weight_class": "55kg",
        "lifter_name": "Stephanie Kennedy",
        "lifter_id": 34516,
        "membershipNumbers": [
          {
            "athleteName": "Stephanie Kennedy",
            "membershipNumber": "1064080",
            "fullText": "3  -  142  Stephanie Kennedy  F  31  Greenville Weightlifting  1064080  52.65  2023-02-11  -  Local  Carolina"
          }
        ],
        "sport80Url": "https://usaweightlifting.sport80.com/public/rankings/all?filters=eyJkYXRlX3JhbmdlX3N0YXJ0IjoiMjAyMy0wMi0xMSIsImRhdGVfcmFuZ2VfZW5kIjoiMjAyMy0wMi0xMSIsIndlaWdodF9jbGFzcyI6OTN9"
      },
      {
        "meet_id": 5999,
        "date": "2023-08-12",
        "age_category": "Open Women's",
        "weight_class": "55kg",
        "lifter_name": "Stephanie Kennedy",
        "lifter_id": 34516,
        "membershipNumbers": [
          {
            "athleteName": "Stephanie Kennedy",
            "membershipNumber": "1064080",
            "fullText": "2  -  153  Stephanie Kennedy  F  31  Greenville Weightlifting  1064080  54.4  2023-08-12  -  Local  Carolina"
          }
        ],
        "sport80Url": "https://usaweightlifting.sport80.com/public/rankings/all?filters=eyJkYXRlX3JhbmdlX3N0YXJ0IjoiMjAyMy0wOC0xMiIsImRhdGVfcmFuZ2VfZW5kIjoiMjAyMy0wOC0xMiIsIndlaWdodF9jbGFzcyI6OTN9"
      },
      {
        "meet_id": 6172,
        "date": "2023-12-07",
        "age_category": "Open Women's",
        "weight_class": "55kg",
        "lifter_name": "Stephanie Kennedy",
        "lifter_id": 34516,
        "membershipNumbers": [
          {
            "athleteName": "Stephanie Kennedy",
            "membershipNumber": "1064080",
            "fullText": "13  -  149  Stephanie Kennedy  F  31  Greenville Weightlifting  1064080  53.52  2023-12-07  -  North American Open Series  Carolina"
          }
        ],
        "sport80Url": "https://usaweightlifting.sport80.com/public/rankings/all?filters=eyJkYXRlX3JhbmdlX3N0YXJ0IjoiMjAyMy0xMi0wNyIsImRhdGVfcmFuZ2VfZW5kIjoiMjAyMy0xMi0wNyIsIndlaWdodF9jbGFzcyI6OTN9"
      },
      {
        "meet_id": 5869,
        "date": "2023-04-22",
        "age_category": "Open Women's",
        "weight_class": "55kg",
        "lifter_name": "Stephanie Kennedy",
        "lifter_id": 34516,
        "membershipNumbers": [
          {
            "athleteName": "Stephanie Kennedy",
            "membershipNumber": "1064080",
            "fullText": "2  -  141  Stephanie Kennedy  F  31  Greenville Weightlifting  1064080  53.6  2023-04-22  -  Local  Carolina"
          }
        ],
        "sport80Url": "https://usaweightlifting.sport80.com/public/rankings/all?filters=eyJkYXRlX3JhbmdlX3N0YXJ0IjoiMjAyMy0wNC0yMiIsImRhdGVfcmFuZ2VfZW5kIjoiMjAyMy0wNC0yMiIsIndlaWdodF9jbGFzcyI6OTN9"
      },
      {
        "meet_id": 6244,
        "date": "2024-02-11",
        "age_category": "Open Women's",
        "weight_class": "55kg",
        "lifter_name": "Stephanie Kennedy",
        "lifter_id": 34516,
        "membershipNumbers": [
          {
            "athleteName": "Stephanie Kennedy",
            "membershipNumber": "1064080",
            "fullText": "2  -  150  Stephanie Kennedy  F  32  Greenville Weightlifting  1064080  54.05  2024-02-11  -  Local  Carolina"
          }
        ],
        "sport80Url": "https://usaweightlifting.sport80.com/public/rankings/all?filters=eyJkYXRlX3JhbmdlX3N0YXJ0IjoiMjAyNC0wMi0xMSIsImRhdGVfcmFuZ2VfZW5kIjoiMjAyNC0wMi0xMSIsIndlaWdodF9jbGFzcyI6OTN9"
      },
      {
        "meet_id": 6506,
        "date": "2024-08-24",
        "age_category": "Open Women's",
        "weight_class": "55kg",
        "lifter_name": "Stephanie Kennedy",
        "lifter_id": 34516,
        "membershipNumbers": [
          {
            "athleteName": "Stephanie Kennedy",
            "membershipNumber": "1064080",
            "fullText": "1  -  153  Stephanie Kennedy  F  32  Greenville Weightlifting  1064080  54.85  2024-08-24  -  Local  Carolina"
          }
        ],
        "sport80Url": "https://usaweightlifting.sport80.com/public/rankings/all?filters=eyJkYXRlX3JhbmdlX3N0YXJ0IjoiMjAyNC0wOC0yNCIsImRhdGVfcmFuZ2VfZW5kIjoiMjAyNC0wOC0yNCIsIndlaWdodF9jbGFzcyI6OTN9"
      },
      {
        "meet_id": 6778,
        "date": "2025-02-27",
        "age_category": "Open Women's",
        "weight_class": "59kg",
        "lifter_name": "Stephanie Kennedy",
        "lifter_id": 34516,
        "membershipNumbers": [
          {
            "athleteName": "Stephanie Kennedy",
            "membershipNumber": "1064080",
            "fullText": "15  -  154  Stephanie Kennedy  F  33  Greenville Weightlifting  1064080  56.07  2025-02-27  -  North American Open Series  Carolina"
          }
        ],
        "sport80Url": "https://usaweightlifting.sport80.com/public/rankings/all?filters=eyJkYXRlX3JhbmdlX3N0YXJ0IjoiMjAyNS0wMi0yNyIsImRhdGVfcmFuZ2VfZW5kIjoiMjAyNS0wMi0yNyIsIndlaWdodF9jbGFzcyI6OTR9"
      },
      {
        "meet_id": 2951,
        "date": "2018-03-18",
        "age_category": "Open Women's",
        "weight_class": "90 kg",
        "lifter_name": "Stephanie Kennedy",
        "lifter_id": 34516,
        "membershipNumbers": [
          {
            "athleteName": "Stephanie Kennedy",
            "membershipNumber": "217283",
            "fullText": "4  -  131  Stephanie Kennedy  F  34  LEHIGH VALLEY BARBELL CLUB  217283  79.75  2018-03-18  -  Local  Pennsylvania-West Virginia"
          }
        ],
        "sport80Url": "https://usaweightlifting.sport80.com/public/rankings/all?filters=eyJkYXRlX3JhbmdlX3N0YXJ0IjoiMjAxOC0wMy0xOCIsImRhdGVfcmFuZ2VfZW5kIjoiMjAxOC0wMy0xOCIsIndlaWdodF9jbGFzcyI6MzY5fQ=="
      },
      {
        "meet_id": 5478,
        "date": "2022-08-27",
        "age_category": "Open Women's",
        "weight_class": "55kg",
        "lifter_name": "Stephanie Kennedy",
        "lifter_id": 34516,
        "membershipNumbers": [
          {
            "athleteName": "Stephanie Kennedy",
            "membershipNumber": "1064080",
            "fullText": "1  -  144  Stephanie Kennedy  F  30  Greenville Weightlifting  1064080  51.85  2022-08-27  -  Local  Carolina"
          }
        ],
        "sport80Url": "https://usaweightlifting.sport80.com/public/rankings/all?filters=eyJkYXRlX3JhbmdlX3N0YXJ0IjoiMjAyMi0wOC0yNyIsImRhdGVfcmFuZ2VfZW5kIjoiMjAyMi0wOC0yNyIsIndlaWdodF9jbGFzcyI6OTN9"
      },
      {
        "meet_id": 6950,
        "date": "2025-06-27",
        "age_category": "Open Women's",
        "weight_class": "58kg",
        "lifter_name": "Stephanie Kennedy",
        "lifter_id": 34516,
        "membershipNumbers": [
          {
            "athleteName": "Stephanie Kennedy",
            "membershipNumber": "1064080",
            "fullText": "13  -  158  Stephanie Kennedy  F  33  Greenville Weightlifting  1064080  56.65  2025-06-27  -  National  Carolina"
          }
        ],
        "sport80Url": "https://usaweightlifting.sport80.com/public/rankings/all?filters=eyJkYXRlX3JhbmdlX3N0YXJ0IjoiMjAyNS0wNi0yNyIsImRhdGVfcmFuZ2VfZW5kIjoiMjAyNS0wNi0yNyIsIndlaWdodF9jbGFzcyI6NzA3fQ=="
      },
      {
        "meet_id": 6582,
        "date": "2024-10-19",
        "age_category": "Open Women's",
        "weight_class": "59kg",
        "lifter_name": "Stephanie Kennedy",
        "lifter_id": 34516,
        "membershipNumbers": [
          {
            "athleteName": "Stephanie Kennedy",
            "membershipNumber": "1064080",
            "fullText": "2  -  150  Stephanie Kennedy  F  32  Greenville Weightlifting  1064080  56.7  2024-10-19  -  Local  Carolina"
          }
        ],
        "sport80Url": "https://usaweightlifting.sport80.com/public/rankings/all?filters=eyJkYXRlX3JhbmdlX3N0YXJ0IjoiMjAyNC0xMC0xOSIsImRhdGVfcmFuZ2VfZW5kIjoiMjAyNC0xMC0xOSIsIndlaWdodF9jbGFzcyI6OTR9"
      },
      {
        "meet_id": 6044,
        "date": "2023-10-14",
        "age_category": "Open Women's",
        "weight_class": "55kg",
        "lifter_name": "Stephanie Kennedy",
        "lifter_id": 34516,
        "membershipNumbers": [
          {
            "athleteName": "Stephanie Kennedy",
            "membershipNumber": "1064080",
            "fullText": "1  -  152  Stephanie Kennedy  F  31  Greenville Weightlifting  1064080  53.65  2023-10-14  -  Local  Carolina"
          }
        ],
        "sport80Url": "https://usaweightlifting.sport80.com/public/rankings/all?filters=eyJkYXRlX3JhbmdlX3N0YXJ0IjoiMjAyMy0xMC0xNCIsImRhdGVfcmFuZ2VfZW5kIjoiMjAyMy0xMC0xNCIsIndlaWdodF9jbGFzcyI6OTN9"
      }
    ],
    "analysis": {
      "distinctAthletes": 2,
      "membershipGroups": {
        "217283": [
          {
            "meet_id": 2951,
            "date": "2018-03-18",
            "age_category": "Open Women's",
            "weight_class": "90 kg",
            "lifter_name": "Stephanie Kennedy",
            "lifter_id": 34516,
            "membershipNumbers": [
              {
                "athleteName": "Stephanie Kennedy",
                "membershipNumber": "217283",
                "fullText": "4  -  131  Stephanie Kennedy  F  34  LEHIGH VALLEY BARBELL CLUB  217283  79.75  2018-03-18  -  Local  Pennsylvania-West Virginia"
              }
            ],
            "sport80Url": "https://usaweightlifting.sport80.com/public/rankings/all?filters=eyJkYXRlX3JhbmdlX3N0YXJ0IjoiMjAxOC0wMy0xOCIsImRhdGVfcmFuZ2VfZW5kIjoiMjAxOC0wMy0xOCIsIndlaWdodF9jbGFzcyI6MzY5fQ=="
          }
        ],
        "1064080": [
          {
            "meet_id": 5717,
            "date": "2023-02-11",
            "age_category": "Open Women's",
            "weight_class": "55kg",
            "lifter_name": "Stephanie Kennedy",
            "lifter_id": 34516,
            "membershipNumbers": [
              {
                "athleteName": "Stephanie Kennedy",
                "membershipNumber": "1064080",
                "fullText": "3  -  142  Stephanie Kennedy  F  31  Greenville Weightlifting  1064080  52.65  2023-02-11  -  Local  Carolina"
              }
            ],
            "sport80Url": "https://usaweightlifting.sport80.com/public/rankings/all?filters=eyJkYXRlX3JhbmdlX3N0YXJ0IjoiMjAyMy0wMi0xMSIsImRhdGVfcmFuZ2VfZW5kIjoiMjAyMy0wMi0xMSIsIndlaWdodF9jbGFzcyI6OTN9"
          },
          {
            "meet_id": 5999,
            "date": "2023-08-12",
            "age_category": "Open Women's",
            "weight_class": "55kg",
            "lifter_name": "Stephanie Kennedy",
            "lifter_id": 34516,
            "membershipNumbers": [
              {
                "athleteName": "Stephanie Kennedy",
                "membershipNumber": "1064080",
                "fullText": "2  -  153  Stephanie Kennedy  F  31  Greenville Weightlifting  1064080  54.4  2023-08-12  -  Local  Carolina"
              }
            ],
            "sport80Url": "https://usaweightlifting.sport80.com/public/rankings/all?filters=eyJkYXRlX3JhbmdlX3N0YXJ0IjoiMjAyMy0wOC0xMiIsImRhdGVfcmFuZ2VfZW5kIjoiMjAyMy0wOC0xMiIsIndlaWdodF9jbGFzcyI6OTN9"
          },
          {
            "meet_id": 6172,
            "date": "2023-12-07",
            "age_category": "Open Women's",
            "weight_class": "55kg",
            "lifter_name": "Stephanie Kennedy",
            "lifter_id": 34516,
            "membershipNumbers": [
              {
                "athleteName": "Stephanie Kennedy",
                "membershipNumber": "1064080",
                "fullText": "13  -  149  Stephanie Kennedy  F  31  Greenville Weightlifting  1064080  53.52  2023-12-07  -  North American Open Series  Carolina"
              }
            ],
            "sport80Url": "https://usaweightlifting.sport80.com/public/rankings/all?filters=eyJkYXRlX3JhbmdlX3N0YXJ0IjoiMjAyMy0xMi0wNyIsImRhdGVfcmFuZ2VfZW5kIjoiMjAyMy0xMi0wNyIsIndlaWdodF9jbGFzcyI6OTN9"
          },
          {
            "meet_id": 5869,
            "date": "2023-04-22",
            "age_category": "Open Women's",
            "weight_class": "55kg",
            "lifter_name": "Stephanie Kennedy",
            "lifter_id": 34516,
            "membershipNumbers": [
              {
                "athleteName": "Stephanie Kennedy",
                "membershipNumber": "1064080",
                "fullText": "2  -  141  Stephanie Kennedy  F  31  Greenville Weightlifting  1064080  53.6  2023-04-22  -  Local  Carolina"
              }
            ],
            "sport80Url": "https://usaweightlifting.sport80.com/public/rankings/all?filters=eyJkYXRlX3JhbmdlX3N0YXJ0IjoiMjAyMy0wNC0yMiIsImRhdGVfcmFuZ2VfZW5kIjoiMjAyMy0wNC0yMiIsIndlaWdodF9jbGFzcyI6OTN9"
          },
          {
            "meet_id": 6244,
            "date": "2024-02-11",
            "age_category": "Open Women's",
            "weight_class": "55kg",
            "lifter_name": "Stephanie Kennedy",
            "lifter_id": 34516,
            "membershipNumbers": [
              {
                "athleteName": "Stephanie Kennedy",
                "membershipNumber": "1064080",
                "fullText": "2  -  150  Stephanie Kennedy  F  32  Greenville Weightlifting  1064080  54.05  2024-02-11  -  Local  Carolina"
              }
            ],
            "sport80Url": "https://usaweightlifting.sport80.com/public/rankings/all?filters=eyJkYXRlX3JhbmdlX3N0YXJ0IjoiMjAyNC0wMi0xMSIsImRhdGVfcmFuZ2VfZW5kIjoiMjAyNC0wMi0xMSIsIndlaWdodF9jbGFzcyI6OTN9"
          },
          {
            "meet_id": 6506,
            "date": "2024-08-24",
            "age_category": "Open Women's",
            "weight_class": "55kg",
            "lifter_name": "Stephanie Kennedy",
            "lifter_id": 34516,
            "membershipNumbers": [
              {
                "athleteName": "Stephanie Kennedy",
                "membershipNumber": "1064080",
                "fullText": "1  -  153  Stephanie Kennedy  F  32  Greenville Weightlifting  1064080  54.85  2024-08-24  -  Local  Carolina"
              }
            ],
            "sport80Url": "https://usaweightlifting.sport80.com/public/rankings/all?filters=eyJkYXRlX3JhbmdlX3N0YXJ0IjoiMjAyNC0wOC0yNCIsImRhdGVfcmFuZ2VfZW5kIjoiMjAyNC0wOC0yNCIsIndlaWdodF9jbGFzcyI6OTN9"
          },
          {
            "meet_id": 6778,
            "date": "2025-02-27",
            "age_category": "Open Women's",
            "weight_class": "59kg",
            "lifter_name": "Stephanie Kennedy",
            "lifter_id": 34516,
            "membershipNumbers": [
              {
                "athleteName": "Stephanie Kennedy",
                "membershipNumber": "1064080",
                "fullText": "15  -  154  Stephanie Kennedy  F  33  Greenville Weightlifting  1064080  56.07  2025-02-27  -  North American Open Series  Carolina"
              }
            ],
            "sport80Url": "https://usaweightlifting.sport80.com/public/rankings/all?filters=eyJkYXRlX3JhbmdlX3N0YXJ0IjoiMjAyNS0wMi0yNyIsImRhdGVfcmFuZ2VfZW5kIjoiMjAyNS0wMi0yNyIsIndlaWdodF9jbGFzcyI6OTR9"
          },
          {
            "meet_id": 5478,
            "date": "2022-08-27",
            "age_category": "Open Women's",
            "weight_class": "55kg",
            "lifter_name": "Stephanie Kennedy",
            "lifter_id": 34516,
            "membershipNumbers": [
              {
                "athleteName": "Stephanie Kennedy",
                "membershipNumber": "1064080",
                "fullText": "1  -  144  Stephanie Kennedy  F  30  Greenville Weightlifting  1064080  51.85  2022-08-27  -  Local  Carolina"
              }
            ],
            "sport80Url": "https://usaweightlifting.sport80.com/public/rankings/all?filters=eyJkYXRlX3JhbmdlX3N0YXJ0IjoiMjAyMi0wOC0yNyIsImRhdGVfcmFuZ2VfZW5kIjoiMjAyMi0wOC0yNyIsIndlaWdodF9jbGFzcyI6OTN9"
          },
          {
            "meet_id": 6950,
            "date": "2025-06-27",
            "age_category": "Open Women's",
            "weight_class": "58kg",
            "lifter_name": "Stephanie Kennedy",
            "lifter_id": 34516,
            "membershipNumbers": [
              {
                "athleteName": "Stephanie Kennedy",
                "membershipNumber": "1064080",
                "fullText": "13  -  158  Stephanie Kennedy  F  33  Greenville Weightlifting  1064080  56.65  2025-06-27  -  National  Carolina"
              }
            ],
            "sport80Url": "https://usaweightlifting.sport80.com/public/rankings/all?filters=eyJkYXRlX3JhbmdlX3N0YXJ0IjoiMjAyNS0wNi0yNyIsImRhdGVfcmFuZ2VfZW5kIjoiMjAyNS0wNi0yNyIsIndlaWdodF9jbGFzcyI6NzA3fQ=="
          },
          {
            "meet_id": 6582,
            "date": "2024-10-19",
            "age_category": "Open Women's",
            "weight_class": "59kg",
            "lifter_name": "Stephanie Kennedy",
            "lifter_id": 34516,
            "membershipNumbers": [
              {
                "athleteName": "Stephanie Kennedy",
                "membershipNumber": "1064080",
                "fullText": "2  -  150  Stephanie Kennedy  F  32  Greenville Weightlifting  1064080  56.7  2024-10-19  -  Local  Carolina"
              }
            ],
            "sport80Url": "https://usaweightlifting.sport80.com/public/rankings/all?filters=eyJkYXRlX3JhbmdlX3N0YXJ0IjoiMjAyNC0xMC0xOSIsImRhdGVfcmFuZ2VfZW5kIjoiMjAyNC0xMC0xOSIsIndlaWdodF9jbGFzcyI6OTR9"
          },
          {
            "meet_id": 6044,
            "date": "2023-10-14",
            "age_category": "Open Women's",
            "weight_class": "55kg",
            "lifter_name": "Stephanie Kennedy",
            "lifter_id": 34516,
            "membershipNumbers": [
              {
                "athleteName": "Stephanie Kennedy",
                "membershipNumber": "1064080",
                "fullText": "1  -  152  Stephanie Kennedy  F  31  Greenville Weightlifting  1064080  53.65  2023-10-14  -  Local  Carolina"
              }
            ],
            "sport80Url": "https://usaweightlifting.sport80.com/public/rankings/all?filters=eyJkYXRlX3JhbmdlX3N0YXJ0IjoiMjAyMy0xMC0xNCIsImRhdGVfcmFuZ2VfZW5kIjoiMjAyMy0xMC0xNCIsIndlaWdodF9jbGFzcyI6OTN9"
          }
        ]
      },
      "unidentifiedCompetitions": [
        {
          "meet_id": 5785,
          "date": "2023-04-01",
          "age_category": "Open Women's",
          "weight_class": "55kg",
          "lifter_name": "Stephanie Kennedy",
          "lifter_id": 34516,
          "membershipNumbers": [],
          "sport80Url": "https://usaweightlifting.sport80.com/public/rankings/all?filters=eyJkYXRlX3JhbmdlX3N0YXJ0IjoiMjAyMy0wNC0wMSIsImRhdGVfcmFuZ2VfZW5kIjoiMjAyMy0wNC0wMSIsIndlaWdodF9jbGFzcyI6OTN9"
        }
      ],
      "splitRequired": true
    }
  }
}