{
  "timestamp": "2025-08-22T21:58:05.682Z",
  "athleteName": "Sarah Haggard",
  "totalCompetitions": 30,
  "analysis": {
    "distinctAthletes": 2,
    "membershipGroups": {
      "1006430": [
        {
          "meet_id": 4725,
          "date": "2021-01-15",
          "age_category": "Women's Masters (40-44)",
          "weight_class": "59kg",
          "lifter_name": "Sarah Haggard",
          "lifter_id": 22794,
          "membershipNumbers": [
            {
              "athleteName": "Sarah Haggard",
              "membershipNumber": "1006430",
              "fullText": "2  -  116  Sarah Haggard  F  40  Spoon Barbell Club  1006430  58.7  2021-01-15  -  Local  Texas-Oklahoma"
            }
          ],
          "sport80Url": "https://usaweightlifting.sport80.com/public/rankings/all?filters=eyJkYXRlX3JhbmdlX3N0YXJ0IjoiMjAyMS0wMS0xNSIsImRhdGVfcmFuZ2VfZW5kIjoiMjAyMS0wMS0xNSIsIndlaWdodF9jbGFzcyI6MTM0fQ=="
        },
        {
          "meet_id": 4817,
          "date": "2021-02-27",
          "age_category": "Women's Masters (40-44)",
          "weight_class": "59kg",
          "lifter_name": "Sarah Haggard",
          "lifter_id": 22794,
          "membershipNumbers": [
            {
              "athleteName": "Sarah Haggard",
              "membershipNumber": "1006430",
              "fullText": "1  -  112  Sarah Haggard  F  40  Spoon Barbell Club  1006430  58.71  2021-02-27  -  Local  Texas-Oklahoma"
            }
          ],
          "sport80Url": "https://usaweightlifting.sport80.com/public/rankings/all?filters=eyJkYXRlX3JhbmdlX3N0YXJ0IjoiMjAyMS0wMi0yNyIsImRhdGVfcmFuZ2VfZW5kIjoiMjAyMS0wMi0yNyIsIndlaWdodF9jbGFzcyI6MTM0fQ=="
        },
        {
          "meet_id": 4867,
          "date": "2021-05-08",
          "age_category": "Women's Masters (40-44)",
          "weight_class": "64kg",
          "lifter_name": "Sarah Haggard",
          "lifter_id": 22794,
          "membershipNumbers": [
            {
              "athleteName": "Sarah Haggard",
              "membershipNumber": "1006430",
              "fullText": "5  -  120  Sarah Haggard  F  40  Spoon Barbell Club  1006430  59.9  2021-05-08  -  Local  Texas-Oklahoma"
            }
          ],
          "sport80Url": "https://usaweightlifting.sport80.com/public/rankings/all?filters=eyJkYXRlX3JhbmdlX3N0YXJ0IjoiMjAyMS0wNS0wOCIsImRhdGVfcmFuZ2VfZW5kIjoiMjAyMS0wNS0wOCIsIndlaWdodF9jbGFzcyI6MTM1fQ=="
        },
        {
          "meet_id": 5331,
          "date": "2022-05-14",
          "age_category": "Women's Masters (40-44)",
          "weight_class": "59kg",
          "lifter_name": "Sarah Haggard",
          "lifter_id": 22794,
          "membershipNumbers": [
            {
              "athleteName": "Sarah Haggard",
              "membershipNumber": "1006430",
              "fullText": "2  -  108  Sarah Haggard  F  41  Spoon Barbell Club  1006430  58.91  2022-05-14  -  Local  Texas-Oklahoma"
            }
          ],
          "sport80Url": "https://usaweightlifting.sport80.com/public/rankings/all?filters=eyJkYXRlX3JhbmdlX3N0YXJ0IjoiMjAyMi0wNS0xNCIsImRhdGVfcmFuZ2VfZW5kIjoiMjAyMi0wNS0xNCIsIndlaWdodF9jbGFzcyI6MTM0fQ=="
        },
        {
          "meet_id": 1766,
          "date": "2016-07-09",
          "age_category": "Women's Masters (35-39)",
          "weight_class": "58 kg",
          "lifter_name": "Sarah Haggard",
          "lifter_id": 22794,
          "membershipNumbers": [
            {
              "athleteName": "Sarah Haggard",
              "membershipNumber": "1006430",
              "fullText": "6  -  92  Sarah Haggard  F  35  Spoon Barbell Club  1006430  57.1  2016-07-09  -  Local  Texas-Oklahoma"
            }
          ],
          "sport80Url": "https://usaweightlifting.sport80.com/public/rankings/all?filters=eyJkYXRlX3JhbmdlX3N0YXJ0IjoiMjAxNi0wNy0wOSIsImRhdGVfcmFuZ2VfZW5kIjoiMjAxNi0wNy0wOSIsIndlaWdodF9jbGFzcyI6MzgxfQ=="
        },
        {
          "meet_id": 2217,
          "date": "2016-10-16",
          "age_category": "Women's Masters (35-39)",
          "weight_class": "58 kg",
          "lifter_name": "Sarah Haggard",
          "lifter_id": 22794,
          "membershipNumbers": [
            {
              "athleteName": "Sarah Haggard",
              "membershipNumber": "1006430",
              "fullText": "4  -  109  Sarah Haggard  F  35  Spoon Barbell Club  1006430  56.95  2016-10-16  -  Local  Texas-Oklahoma"
            }
          ],
          "sport80Url": "https://usaweightlifting.sport80.com/public/rankings/all?filters=eyJkYXRlX3JhbmdlX3N0YXJ0IjoiMjAxNi0xMC0xNiIsImRhdGVfcmFuZ2VfZW5kIjoiMjAxNi0xMC0xNiIsIndlaWdodF9jbGFzcyI6MzgxfQ=="
        },
        {
          "meet_id": 2356,
          "date": "2017-01-15",
          "age_category": "Women's Masters (35-39)",
          "weight_class": "58 kg",
          "lifter_name": "Sarah Haggard",
          "lifter_id": 22794,
          "membershipNumbers": [
            {
              "athleteName": "Sarah Haggard",
              "membershipNumber": "1006430",
              "fullText": "6  -  108  Sarah Haggard  F  36  Spoon Barbell Club  1006430  56.8  2017-01-15  -  Local  Texas-Oklahoma"
            }
          ],
          "sport80Url": "https://usaweightlifting.sport80.com/public/rankings/all?filters=eyJkYXRlX3JhbmdlX3N0YXJ0IjoiMjAxNy0wMS0xNSIsImRhdGVfcmFuZ2VfZW5kIjoiMjAxNy0wMS0xNSIsIndlaWdodF9jbGFzcyI6MzgxfQ=="
        },
        {
          "meet_id": 2622,
          "date": "2017-05-21",
          "age_category": "Women's Masters (35-39)",
          "weight_class": "58 kg",
          "lifter_name": "Sarah Haggard",
          "lifter_id": 22794,
          "membershipNumbers": [
            {
              "athleteName": "Sarah Haggard",
              "membershipNumber": "1006430",
              "fullText": "2  -  119  Sarah Haggard  F  36  Spoon Barbell Club  1006430  57.3  2017-05-21  -  Local  Texas-Oklahoma"
            }
          ],
          "sport80Url": "https://usaweightlifting.sport80.com/public/rankings/all?filters=eyJkYXRlX3JhbmdlX3N0YXJ0IjoiMjAxNy0wNS0yMSIsImRhdGVfcmFuZ2VfZW5kIjoiMjAxNy0wNS0yMSIsIndlaWdodF9jbGFzcyI6MzgxfQ=="
        },
        {
          "meet_id": 2780,
          "date": "2017-10-29",
          "age_category": "Women's Masters (35-39)",
          "weight_class": "63 kg",
          "lifter_name": "Sarah Haggard",
          "lifter_id": 22794,
          "membershipNumbers": [
            {
              "athleteName": "Sarah Haggard",
              "membershipNumber": "1006430",
              "fullText": "6  -  119  Sarah Haggard  F  36  Spoon Barbell Club  1006430  58.2  2017-10-29  -  Local  Texas-Oklahoma"
            }
          ],
          "sport80Url": "https://usaweightlifting.sport80.com/public/rankings/all?filters=eyJkYXRlX3JhbmdlX3N0YXJ0IjoiMjAxNy0xMC0yOSIsImRhdGVfcmFuZ2VfZW5kIjoiMjAxNy0xMC0yOSIsIndlaWdodF9jbGFzcyI6MzgyfQ=="
        },
        {
          "meet_id": 2802,
          "date": "2017-10-15",
          "age_category": "Women's Masters (35-39)",
          "weight_class": "58 kg",
          "lifter_name": "Sarah Haggard",
          "lifter_id": 22794,
          "membershipNumbers": [
            {
              "athleteName": "Sarah Haggard",
              "membershipNumber": "1006430",
              "fullText": "4  -  119  Sarah Haggard  F  36  Spoon Barbell Club  1006430  57.92  2017-10-15  -  Local  Texas-Oklahoma"
            }
          ],
          "sport80Url": "https://usaweightlifting.sport80.com/public/rankings/all?filters=eyJkYXRlX3JhbmdlX3N0YXJ0IjoiMjAxNy0xMC0xNSIsImRhdGVfcmFuZ2VfZW5kIjoiMjAxNy0xMC0xNSIsIndlaWdodF9jbGFzcyI6MzgxfQ=="
        },
        {
          "meet_id": 2939,
          "date": "2018-01-14",
          "age_category": "Women's Masters (35-39)",
          "weight_class": "58 kg",
          "lifter_name": "Sarah Haggard",
          "lifter_id": 22794,
          "membershipNumbers": [
            {
              "athleteName": "Sarah Haggard",
              "membershipNumber": "1006430",
              "fullText": "5  -  125  Sarah Haggard  F  37  Spoon Barbell Club  1006430  58  2018-01-14  -  Local  Texas-Oklahoma"
            }
          ],
          "sport80Url": "https://usaweightlifting.sport80.com/public/rankings/all?filters=eyJkYXRlX3JhbmdlX3N0YXJ0IjoiMjAxOC0wMS0xNCIsImRhdGVfcmFuZ2VfZW5kIjoiMjAxOC0wMS0xNCIsIndlaWdodF9jbGFzcyI6MzgxfQ=="
        },
        {
          "meet_id": 3072,
          "date": "2018-03-31",
          "age_category": "Women's Masters (35-39)",
          "weight_class": "58 kg",
          "lifter_name": "Sarah Haggard",
          "lifter_id": 22794,
          "membershipNumbers": [
            {
              "athleteName": "Sarah Haggard",
              "membershipNumber": "1006430",
              "fullText": "1  -  128  Sarah Haggard  F  37  Spoon Barbell Club  1006430  57.9  2018-03-31  -  Local  Texas-Oklahoma"
            }
          ],
          "sport80Url": "https://usaweightlifting.sport80.com/public/rankings/all?filters=eyJkYXRlX3JhbmdlX3N0YXJ0IjoiMjAxOC0wMy0zMSIsImRhdGVfcmFuZ2VfZW5kIjoiMjAxOC0wMy0zMSIsIndlaWdodF9jbGFzcyI6MzgxfQ=="
        },
        {
          "meet_id": 3180,
          "date": "2018-05-06",
          "age_category": "Women's Masters (35-39)",
          "weight_class": "58 kg",
          "lifter_name": "Sarah Haggard",
          "lifter_id": 22794,
          "membershipNumbers": [
            {
              "athleteName": "Sarah Haggard",
              "membershipNumber": "1006430",
              "fullText": "1  -  129  Sarah Haggard  F  37  Spoon Barbell Club  1006430  57.99  2018-05-06  -  Local  Texas-Oklahoma"
            }
          ],
          "sport80Url": "https://usaweightlifting.sport80.com/public/rankings/all?filters=eyJkYXRlX3JhbmdlX3N0YXJ0IjoiMjAxOC0wNS0wNiIsImRhdGVfcmFuZ2VfZW5kIjoiMjAxOC0wNS0wNiIsIndlaWdodF9jbGFzcyI6MzgxfQ=="
        },
        {
          "meet_id": 3276,
          "date": "2018-03-23",
          "age_category": "Women's Masters (35-39)",
          "weight_class": "58 kg",
          "lifter_name": "Sarah Haggard",
          "lifter_id": 22794,
          "membershipNumbers": [
            {
              "athleteName": "Sarah Haggard",
              "membershipNumber": "1006430",
              "fullText": "1  -  128  Sarah Haggard  F  37  Spoon Barbell Club  1006430  58  2018-03-23  -  Local  Texas-Oklahoma"
            }
          ],
          "sport80Url": "https://usaweightlifting.sport80.com/public/rankings/all?filters=eyJkYXRlX3JhbmdlX3N0YXJ0IjoiMjAxOC0wMy0yMyIsImRhdGVfcmFuZ2VfZW5kIjoiMjAxOC0wMy0yMyIsIndlaWdodF9jbGFzcyI6MzgxfQ=="
        },
        {
          "meet_id": 3353,
          "date": "2018-07-22",
          "age_category": "Women's Masters (35-39)",
          "weight_class": "58 kg",
          "lifter_name": "Sarah Haggard",
          "lifter_id": 22794,
          "membershipNumbers": [
            {
              "athleteName": "Sarah Haggard",
              "membershipNumber": "1006430",
              "fullText": "6  -  120  Sarah Haggard  F  37  Spoon Barbell Club  1006430  57.7  2018-07-22  -  Local  Texas-Oklahoma"
            }
          ],
          "sport80Url": "https://usaweightlifting.sport80.com/public/rankings/all?filters=eyJkYXRlX3JhbmdlX3N0YXJ0IjoiMjAxOC0wNy0yMiIsImRhdGVfcmFuZ2VfZW5kIjoiMjAxOC0wNy0yMiIsIndlaWdodF9jbGFzcyI6MzgxfQ=="
        },
        {
          "meet_id": 3454,
          "date": "2018-10-07",
          "age_category": "Women's Masters (35-39)",
          "weight_class": "59kg",
          "lifter_name": "Sarah Haggard",
          "lifter_id": 22794,
          "membershipNumbers": [
            {
              "athleteName": "Sarah Haggard",
              "membershipNumber": "1006430",
              "fullText": "2  -  124  Sarah Haggard  F  37  Spoon Barbell Club  1006430  58.1  2018-10-07  -  Local  Texas-Oklahoma"
            }
          ],
          "sport80Url": "https://usaweightlifting.sport80.com/public/rankings/all?filters=eyJkYXRlX3JhbmdlX3N0YXJ0IjoiMjAxOC0xMC0wNyIsImRhdGVfcmFuZ2VfZW5kIjoiMjAxOC0xMC0wNyIsIndlaWdodF9jbGFzcyI6MTE0fQ=="
        },
        {
          "meet_id": 2074,
          "date": "2016-08-27",
          "age_category": "Women's Masters (35-39)",
          "weight_class": "58 kg",
          "lifter_name": "Sarah Haggard",
          "lifter_id": 22794,
          "membershipNumbers": [
            {
              "athleteName": "Sarah Haggard",
              "membershipNumber": "1006430",
              "fullText": "7  -  103  Sarah Haggard  F  35  Spoon Barbell Club  1006430  57  2016-08-27  -  Local  Texas-Oklahoma"
            }
          ],
          "sport80Url": "https://usaweightlifting.sport80.com/public/rankings/all?filters=eyJkYXRlX3JhbmdlX3N0YXJ0IjoiMjAxNi0wOC0yNyIsImRhdGVfcmFuZ2VfZW5kIjoiMjAxNi0wOC0yNyIsIndlaWdodF9jbGFzcyI6MzgxfQ=="
        },
        {
          "meet_id": 4564,
          "date": "2020-10-17",
          "age_category": "Women's Masters (35-39)",
          "weight_class": "59kg",
          "lifter_name": "Sarah Haggard",
          "lifter_id": 22794,
          "membershipNumbers": [
            {
              "athleteName": "Sarah Haggard",
              "membershipNumber": "1006430",
              "fullText": "1  -  123  Sarah Haggard  F  39  Spoon Barbell Club  1006430  58.5  2020-10-17  -  Local  Texas-Oklahoma"
            }
          ],
          "sport80Url": "https://usaweightlifting.sport80.com/public/rankings/all?filters=eyJkYXRlX3JhbmdlX3N0YXJ0IjoiMjAyMC0xMC0xNyIsImRhdGVfcmFuZ2VfZW5kIjoiMjAyMC0xMC0xNyIsIndlaWdodF9jbGFzcyI6MTE0fQ=="
        },
        {
          "meet_id": 4420,
          "date": "2020-01-17",
          "age_category": "Women's Masters (35-39)",
          "weight_class": "59kg",
          "lifter_name": "Sarah Haggard",
          "lifter_id": 22794,
          "membershipNumbers": [
            {
              "athleteName": "Sarah Haggard",
              "membershipNumber": "1006430",
              "fullText": "2  -  114  Sarah Haggard  F  39  Spoon Barbell Club  1006430  58.1  2020-01-17  -  Local  Texas-Oklahoma"
            }
          ],
          "sport80Url": "https://usaweightlifting.sport80.com/public/rankings/all?filters=eyJkYXRlX3JhbmdlX3N0YXJ0IjoiMjAyMC0wMS0xNyIsImRhdGVfcmFuZ2VfZW5kIjoiMjAyMC0wMS0xNyIsIndlaWdodF9jbGFzcyI6MTE0fQ=="
        },
        {
          "meet_id": 2374,
          "date": "2017-04-02",
          "age_category": "Women's Masters (35-39)",
          "weight_class": "58 kg",
          "lifter_name": "Sarah Haggard",
          "lifter_id": 22794,
          "membershipNumbers": [
            {
              "athleteName": "Sarah Haggard",
              "membershipNumber": "1006430",
              "fullText": "1  -  119  Sarah Haggard  F  36  Spoon Barbell Club  1006430  58  2017-04-02  -  Local  Texas-Oklahoma"
            }
          ],
          "sport80Url": "https://usaweightlifting.sport80.com/public/rankings/all?filters=eyJkYXRlX3JhbmdlX3N0YXJ0IjoiMjAxNy0wNC0wMiIsImRhdGVfcmFuZ2VfZW5kIjoiMjAxNy0wNC0wMiIsIndlaWdodF9jbGFzcyI6MzgxfQ=="
        },
        {
          "meet_id": 3525,
          "date": "2019-01-20",
          "age_category": "Women's Masters (35-39)",
          "weight_class": "59kg",
          "lifter_name": "Sarah Haggard",
          "lifter_id": 22794,
          "membershipNumbers": [
            {
              "athleteName": "Sarah Haggard",
              "membershipNumber": "1006430",
              "fullText": "1  -  120  Sarah Haggard  F  38  Spoon Barbell Club  1006430  58.01  2019-01-20  -  Local  Texas-Oklahoma"
            }
          ],
          "sport80Url": "https://usaweightlifting.sport80.com/public/rankings/all?filters=eyJkYXRlX3JhbmdlX3N0YXJ0IjoiMjAxOS0wMS0yMCIsImRhdGVfcmFuZ2VfZW5kIjoiMjAxOS0wMS0yMCIsIndlaWdodF9jbGFzcyI6MTE0fQ=="
        },
        {
          "meet_id": 3720,
          "date": "2019-03-31",
          "age_category": "Women's Masters (35-39)",
          "weight_class": "59kg",
          "lifter_name": "Sarah Haggard",
          "lifter_id": 22794,
          "membershipNumbers": [
            {
              "athleteName": "Sarah Haggard",
              "membershipNumber": "1006430",
              "fullText": "11  -  120  Sarah Haggard  F  38  Spoon Barbell Club  1006430  58.8  2019-03-31  -  National  Texas-Oklahoma"
            }
          ],
          "sport80Url": "https://usaweightlifting.sport80.com/public/rankings/all?filters=eyJkYXRlX3JhbmdlX3N0YXJ0IjoiMjAxOS0wMy0zMSIsImRhdGVfcmFuZ2VfZW5kIjoiMjAxOS0wMy0zMSIsIndlaWdodF9jbGFzcyI6MTE0fQ=="
        },
        {
          "meet_id": 4178,
          "date": "2019-10-13",
          "age_category": "Women's Masters (35-39)",
          "weight_class": "59kg",
          "lifter_name": "Sarah Haggard",
          "lifter_id": 22794,
          "membershipNumbers": [
            {
              "athleteName": "Sarah Haggard",
              "membershipNumber": "1006430",
              "fullText": "1  -  111  Sarah Haggard  F  38  Spoon Barbell Club  1006430  58.28  2019-10-13  -  Local  Texas-Oklahoma"
            }
          ],
          "sport80Url": "https://usaweightlifting.sport80.com/public/rankings/all?filters=eyJkYXRlX3JhbmdlX3N0YXJ0IjoiMjAxOS0xMC0xMyIsImRhdGVfcmFuZ2VfZW5kIjoiMjAxOS0xMC0xMyIsIndlaWdodF9jbGFzcyI6MTE0fQ=="
        },
        {
          "meet_id": 4543,
          "date": "2020-08-08",
          "age_category": "Women's Masters (35-39)",
          "weight_class": "59kg",
          "lifter_name": "Sarah Haggard",
          "lifter_id": 22794,
          "membershipNumbers": [
            {
              "athleteName": "Sarah Haggard",
              "membershipNumber": "1006430",
              "fullText": "1  -  120  Sarah Haggard  F  39  Spoon Barbell Club  1006430  58.5  2020-08-08  -  Local  Texas-Oklahoma"
            }
          ],
          "sport80Url": "https://usaweightlifting.sport80.com/public/rankings/all?filters=eyJkYXRlX3JhbmdlX3N0YXJ0IjoiMjAyMC0wOC0wOCIsImRhdGVfcmFuZ2VfZW5kIjoiMjAyMC0wOC0wOCIsIndlaWdodF9jbGFzcyI6MTE0fQ=="
        }
      ],
      "1022064": [
        {
          "meet_id": 3384,
          "date": "2018-07-14",
          "age_category": "Open Women's",
          "weight_class": "69 kg",
          "lifter_name": "Sarah Haggard",
          "lifter_id": 22794,
          "membershipNumbers": [
            {
              "athleteName": "Sarah Haggard",
              "membershipNumber": "1022064",
              "fullText": "12  -  130  Sarah Haggard  F  31  -  1022064  67.8  2018-07-14  -  Local  Pacific Northwest"
            }
          ],
          "sport80Url": "https://usaweightlifting.sport80.com/public/rankings/all?filters=eyJkYXRlX3JhbmdlX3N0YXJ0IjoiMjAxOC0wNy0xNCIsImRhdGVfcmFuZ2VfZW5kIjoiMjAxOC0wNy0xNCIsIndlaWdodF9jbGFzcyI6MzY2fQ=="
        },
        {
          "meet_id": 3854,
          "date": "2019-03-23",
          "age_category": "Open Women's",
          "weight_class": "76kg",
          "lifter_name": "Sarah Haggard",
          "lifter_id": 22794,
          "membershipNumbers": [
            {
              "athleteName": "Sarah Haggard",
              "membershipNumber": "1022064",
              "fullText": "8  -  132  Sarah Haggard  F  32  -  1022064  73  2019-03-23  -  Local  Pacific Northwest"
            }
          ],
          "sport80Url": "https://usaweightlifting.sport80.com/public/rankings/all?filters=eyJkYXRlX3JhbmdlX3N0YXJ0IjoiMjAxOS0wMy0yMyIsImRhdGVfcmFuZ2VfZW5kIjoiMjAxOS0wMy0yMyIsIndlaWdodF9jbGFzcyI6OTd9"
        },
        {
          "meet_id": 2967,
          "date": "2018-01-27",
          "age_category": "Open Women's",
          "weight_class": "69 kg",
          "lifter_name": "Sarah Haggard",
          "lifter_id": 22794,
          "membershipNumbers": [
            {
              "athleteName": "Sarah Haggard",
              "membershipNumber": "1022064",
              "fullText": "18  -  119  Sarah Haggard  F  31  -  1022064  68.4  2018-01-27  -  Local  Pacific Northwest"
            }
          ],
          "sport80Url": "https://usaweightlifting.sport80.com/public/rankings/all?filters=eyJkYXRlX3JhbmdlX3N0YXJ0IjoiMjAxOC0wMS0yNyIsImRhdGVfcmFuZ2VfZW5kIjoiMjAxOC0wMS0yNyIsIndlaWdodF9jbGFzcyI6MzY2fQ=="
        },
        {
          "meet_id": 5863,
          "date": "2023-05-13",
          "age_category": "Women's Masters (35-39)",
          "weight_class": "76kg",
          "lifter_name": "Sarah Haggard",
          "lifter_id": 22794,
          "membershipNumbers": [
            {
              "athleteName": "Sarah Haggard",
              "membershipNumber": "1022064",
              "fullText": "4  -  119  Sarah Haggard  F  36  -  1022064  74.8  2023-05-13  -  Local  Pacific Northwest"
            }
          ],
          "sport80Url": "https://usaweightlifting.sport80.com/public/rankings/all?filters=eyJkYXRlX3JhbmdlX3N0YXJ0IjoiMjAyMy0wNS0xMyIsImRhdGVfcmFuZ2VfZW5kIjoiMjAyMy0wNS0xMyIsIndlaWdodF9jbGFzcyI6MTE3fQ=="
        }
      ]
    },
    "unidentifiedCompetitions": [
      {
        "meet_id": 2766,
        "date": "2017-10-21",
        "age_category": "Open Women's",
        "weight_class": "69 kg",
        "lifter_name": "Sarah Haggard",
        "lifter_id": 22794,
        "membershipNumbers": [],
        "sport80Url": "https://usaweightlifting.sport80.com/public/rankings/all?filters=eyJkYXRlX3JhbmdlX3N0YXJ0IjoiMjAxNy0xMC0yMSIsImRhdGVfcmFuZ2VfZW5kIjoiMjAxNy0xMC0yMSIsIndlaWdodF9jbGFzcyI6MzY2fQ=="
      },
      {
        "meet_id": 2891,
        "date": "2018-09-16",
        "age_category": "Open Women's",
        "weight_class": "71kg",
        "lifter_name": "Sarah Haggard",
        "lifter_id": 22794,
        "membershipNumbers": [],
        "sport80Url": "https://usaweightlifting.sport80.com/public/rankings/all?filters=eyJkYXRlX3JhbmdlX3N0YXJ0IjoiMjAxOC0wOS0xNiIsImRhdGVfcmFuZ2VfZW5kIjoiMjAxOC0wOS0xNiIsIndlaWdodF9jbGFzcyI6OTZ9"
      }
    ],
    "splitRequired": true
  },
  "splitPlan": {
    "action": "SPLIT_REQUIRED",
    "originalAthleteName": "Sarah Haggard",
    "splits": [
      {
        "newAthleteName": "Sarah Haggard (Person 1)",
        "membershipNumber": "1006430",
        "competitionCount": 24,
        "competitions": [
          4725,
          4817,
          4867,
          5331,
          1766,
          2217,
          2356,
          2622,
          2780,
          2802,
          2939,
          3072,
          3180,
          3276,
          3353,
          3454,
          2074,
          4564,
          4420,
          2374,
          3525,
          3720,
          4178,
          4543
        ]
      },
      {
        "newAthleteName": "Sarah Haggard (Person 2)",
        "membershipNumber": "1022064",
        "competitionCount": 4,
        "competitions": [
          3384,
          3854,
          2967,
          5863
        ]
      }
    ],
    "unidentifiedCompetitions": [
      {
        "meet_id": 2766,
        "date": "2017-10-21",
        "age_category": "Open Women's",
        "weight_class": "69 kg",
        "lifter_name": "Sarah Haggard",
        "lifter_id": 22794,
        "membershipNumbers": [],
        "sport80Url": "https://usaweightlifting.sport80.com/public/rankings/all?filters=eyJkYXRlX3JhbmdlX3N0YXJ0IjoiMjAxNy0xMC0yMSIsImRhdGVfcmFuZ2VfZW5kIjoiMjAxNy0xMC0yMSIsIndlaWdodF9jbGFzcyI6MzY2fQ=="
      },
      {
        "meet_id": 2891,
        "date": "2018-09-16",
        "age_category": "Open Women's",
        "weight_class": "71kg",
        "lifter_name": "Sarah Haggard",
        "lifter_id": 22794,
        "membershipNumbers": [],
        "sport80Url": "https://usaweightlifting.sport80.com/public/rankings/all?filters=eyJkYXRlX3JhbmdlX3N0YXJ0IjoiMjAxOC0wOS0xNiIsImRhdGVfcmFuZ2VfZW5kIjoiMjAxOC0wOS0xNiIsIndlaWdodF9jbGFzcyI6OTZ9"
      }
    ]
  },
  "rawData": {
    "athleteName": "Sarah Haggard",
    "competitions": [
      {
        "meet_id": 4725,
        "date": "2021-01-15",
        "age_category": "Women's Masters (40-44)",
        "weight_class": "59kg",
        "lifter_name": "Sarah Haggard",
        "lifter_id": 22794,
        "membershipNumbers": [
          {
            "athleteName": "Sarah Haggard",
            "membershipNumber": "1006430",
            "fullText": "2  -  116  Sarah Haggard  F  40  Spoon Barbell Club  1006430  58.7  2021-01-15  -  Local  Texas-Oklahoma"
          }
        ],
        "sport80Url": "https://usaweightlifting.sport80.com/public/rankings/all?filters=eyJkYXRlX3JhbmdlX3N0YXJ0IjoiMjAyMS0wMS0xNSIsImRhdGVfcmFuZ2VfZW5kIjoiMjAyMS0wMS0xNSIsIndlaWdodF9jbGFzcyI6MTM0fQ=="
      },
      {
        "meet_id": 4817,
        "date": "2021-02-27",
        "age_category": "Women's Masters (40-44)",
        "weight_class": "59kg",
        "lifter_name": "Sarah Haggard",
        "lifter_id": 22794,
        "membershipNumbers": [
          {
            "athleteName": "Sarah Haggard",
            "membershipNumber": "1006430",
            "fullText": "1  -  112  Sarah Haggard  F  40  Spoon Barbell Club  1006430  58.71  2021-02-27  -  Local  Texas-Oklahoma"
          }
        ],
        "sport80Url": "https://usaweightlifting.sport80.com/public/rankings/all?filters=eyJkYXRlX3JhbmdlX3N0YXJ0IjoiMjAyMS0wMi0yNyIsImRhdGVfcmFuZ2VfZW5kIjoiMjAyMS0wMi0yNyIsIndlaWdodF9jbGFzcyI6MTM0fQ=="
      },
      {
        "meet_id": 4867,
        "date": "2021-05-08",
        "age_category": "Women's Masters (40-44)",
        "weight_class": "64kg",
        "lifter_name": "Sarah Haggard",
        "lifter_id": 22794,
        "membershipNumbers": [
          {
            "athleteName": "Sarah Haggard",
            "membershipNumber": "1006430",
            "fullText": "5  -  120  Sarah Haggard  F  40  Spoon Barbell Club  1006430  59.9  2021-05-08  -  Local  Texas-Oklahoma"
          }
        ],
        "sport80Url": "https://usaweightlifting.sport80.com/public/rankings/all?filters=eyJkYXRlX3JhbmdlX3N0YXJ0IjoiMjAyMS0wNS0wOCIsImRhdGVfcmFuZ2VfZW5kIjoiMjAyMS0wNS0wOCIsIndlaWdodF9jbGFzcyI6MTM1fQ=="
      },
      {
        "meet_id": 5331,
        "date": "2022-05-14",
        "age_category": "Women's Masters (40-44)",
        "weight_class": "59kg",
        "lifter_name": "Sarah Haggard",
        "lifter_id": 22794,
        "membershipNumbers": [
          {
            "athleteName": "Sarah Haggard",
            "membershipNumber": "1006430",
            "fullText": "2  -  108  Sarah Haggard  F  41  Spoon Barbell Club  1006430  58.91  2022-05-14  -  Local  Texas-Oklahoma"
          }
        ],
        "sport80Url": "https://usaweightlifting.sport80.com/public/rankings/all?filters=eyJkYXRlX3JhbmdlX3N0YXJ0IjoiMjAyMi0wNS0xNCIsImRhdGVfcmFuZ2VfZW5kIjoiMjAyMi0wNS0xNCIsIndlaWdodF9jbGFzcyI6MTM0fQ=="
      },
      {
        "meet_id": 1766,
        "date": "2016-07-09",
        "age_category": "Women's Masters (35-39)",
        "weight_class": "58 kg",
        "lifter_name": "Sarah Haggard",
        "lifter_id": 22794,
        "membershipNumbers": [
          {
            "athleteName": "Sarah Haggard",
            "membershipNumber": "1006430",
            "fullText": "6  -  92  Sarah Haggard  F  35  Spoon Barbell Club  1006430  57.1  2016-07-09  -  Local  Texas-Oklahoma"
          }
        ],
        "sport80Url": "https://usaweightlifting.sport80.com/public/rankings/all?filters=eyJkYXRlX3JhbmdlX3N0YXJ0IjoiMjAxNi0wNy0wOSIsImRhdGVfcmFuZ2VfZW5kIjoiMjAxNi0wNy0wOSIsIndlaWdodF9jbGFzcyI6MzgxfQ=="
      },
      {
        "meet_id": 2217,
        "date": "2016-10-16",
        "age_category": "Women's Masters (35-39)",
        "weight_class": "58 kg",
        "lifter_name": "Sarah Haggard",
        "lifter_id": 22794,
        "membershipNumbers": [
          {
            "athleteName": "Sarah Haggard",
            "membershipNumber": "1006430",
            "fullText": "4  -  109  Sarah Haggard  F  35  Spoon Barbell Club  1006430  56.95  2016-10-16  -  Local  Texas-Oklahoma"
          }
        ],
        "sport80Url": "https://usaweightlifting.sport80.com/public/rankings/all?filters=eyJkYXRlX3JhbmdlX3N0YXJ0IjoiMjAxNi0xMC0xNiIsImRhdGVfcmFuZ2VfZW5kIjoiMjAxNi0xMC0xNiIsIndlaWdodF9jbGFzcyI6MzgxfQ=="
      },
      {
        "meet_id": 2356,
        "date": "2017-01-15",
        "age_category": "Women's Masters (35-39)",
        "weight_class": "58 kg",
        "lifter_name": "Sarah Haggard",
        "lifter_id": 22794,
        "membershipNumbers": [
          {
            "athleteName": "Sarah Haggard",
            "membershipNumber": "1006430",
            "fullText": "6  -  108  Sarah Haggard  F  36  Spoon Barbell Club  1006430  56.8  2017-01-15  -  Local  Texas-Oklahoma"
          }
        ],
        "sport80Url": "https://usaweightlifting.sport80.com/public/rankings/all?filters=eyJkYXRlX3JhbmdlX3N0YXJ0IjoiMjAxNy0wMS0xNSIsImRhdGVfcmFuZ2VfZW5kIjoiMjAxNy0wMS0xNSIsIndlaWdodF9jbGFzcyI6MzgxfQ=="
      },
      {
        "meet_id": 2622,
        "date": "2017-05-21",
        "age_category": "Women's Masters (35-39)",
        "weight_class": "58 kg",
        "lifter_name": "Sarah Haggard",
        "lifter_id": 22794,
        "membershipNumbers": [
          {
            "athleteName": "Sarah Haggard",
            "membershipNumber": "1006430",
            "fullText": "2  -  119  Sarah Haggard  F  36  Spoon Barbell Club  1006430  57.3  2017-05-21  -  Local  Texas-Oklahoma"
          }
        ],
        "sport80Url": "https://usaweightlifting.sport80.com/public/rankings/all?filters=eyJkYXRlX3JhbmdlX3N0YXJ0IjoiMjAxNy0wNS0yMSIsImRhdGVfcmFuZ2VfZW5kIjoiMjAxNy0wNS0yMSIsIndlaWdodF9jbGFzcyI6MzgxfQ=="
      },
      {
        "meet_id": 2780,
        "date": "2017-10-29",
        "age_category": "Women's Masters (35-39)",
        "weight_class": "63 kg",
        "lifter_name": "Sarah Haggard",
        "lifter_id": 22794,
        "membershipNumbers": [
          {
            "athleteName": "Sarah Haggard",
            "membershipNumber": "1006430",
            "fullText": "6  -  119  Sarah Haggard  F  36  Spoon Barbell Club  1006430  58.2  2017-10-29  -  Local  Texas-Oklahoma"
          }
        ],
        "sport80Url": "https://usaweightlifting.sport80.com/public/rankings/all?filters=eyJkYXRlX3JhbmdlX3N0YXJ0IjoiMjAxNy0xMC0yOSIsImRhdGVfcmFuZ2VfZW5kIjoiMjAxNy0xMC0yOSIsIndlaWdodF9jbGFzcyI6MzgyfQ=="
      },
      {
        "meet_id": 2802,
        "date": "2017-10-15",
        "age_category": "Women's Masters (35-39)",
        "weight_class": "58 kg",
        "lifter_name": "Sarah Haggard",
        "lifter_id": 22794,
        "membershipNumbers": [
          {
            "athleteName": "Sarah Haggard",
            "membershipNumber": "1006430",
            "fullText": "4  -  119  Sarah Haggard  F  36  Spoon Barbell Club  1006430  57.92  2017-10-15  -  Local  Texas-Oklahoma"
          }
        ],
        "sport80Url": "https://usaweightlifting.sport80.com/public/rankings/all?filters=eyJkYXRlX3JhbmdlX3N0YXJ0IjoiMjAxNy0xMC0xNSIsImRhdGVfcmFuZ2VfZW5kIjoiMjAxNy0xMC0xNSIsIndlaWdodF9jbGFzcyI6MzgxfQ=="
      },
      {
        "meet_id": 2939,
        "date": "2018-01-14",
        "age_category": "Women's Masters (35-39)",
        "weight_class": "58 kg",
        "lifter_name": "Sarah Haggard",
        "lifter_id": 22794,
        "membershipNumbers": [
          {
            "athleteName": "Sarah Haggard",
            "membershipNumber": "1006430",
            "fullText": "5  -  125  Sarah Haggard  F  37  Spoon Barbell Club  1006430  58  2018-01-14  -  Local  Texas-Oklahoma"
          }
        ],
        "sport80Url": "https://usaweightlifting.sport80.com/public/rankings/all?filters=eyJkYXRlX3JhbmdlX3N0YXJ0IjoiMjAxOC0wMS0xNCIsImRhdGVfcmFuZ2VfZW5kIjoiMjAxOC0wMS0xNCIsIndlaWdodF9jbGFzcyI6MzgxfQ=="
      },
      {
        "meet_id": 3072,
        "date": "2018-03-31",
        "age_category": "Women's Masters (35-39)",
        "weight_class": "58 kg",
        "lifter_name": "Sarah Haggard",
        "lifter_id": 22794,
        "membershipNumbers": [
          {
            "athleteName": "Sarah Haggard",
            "membershipNumber": "1006430",
            "fullText": "1  -  128  Sarah Haggard  F  37  Spoon Barbell Club  1006430  57.9  2018-03-31  -  Local  Texas-Oklahoma"
          }
        ],
        "sport80Url": "https://usaweightlifting.sport80.com/public/rankings/all?filters=eyJkYXRlX3JhbmdlX3N0YXJ0IjoiMjAxOC0wMy0zMSIsImRhdGVfcmFuZ2VfZW5kIjoiMjAxOC0wMy0zMSIsIndlaWdodF9jbGFzcyI6MzgxfQ=="
      },
      {
        "meet_id": 3180,
        "date": "2018-05-06",
        "age_category": "Women's Masters (35-39)",
        "weight_class": "58 kg",
        "lifter_name": "Sarah Haggard",
        "lifter_id": 22794,
        "membershipNumbers": [
          {
            "athleteName": "Sarah Haggard",
            "membershipNumber": "1006430",
            "fullText": "1  -  129  Sarah Haggard  F  37  Spoon Barbell Club  1006430  57.99  2018-05-06  -  Local  Texas-Oklahoma"
          }
        ],
        "sport80Url": "https://usaweightlifting.sport80.com/public/rankings/all?filters=eyJkYXRlX3JhbmdlX3N0YXJ0IjoiMjAxOC0wNS0wNiIsImRhdGVfcmFuZ2VfZW5kIjoiMjAxOC0wNS0wNiIsIndlaWdodF9jbGFzcyI6MzgxfQ=="
      },
      {
        "meet_id": 3276,
        "date": "2018-03-23",
        "age_category": "Women's Masters (35-39)",
        "weight_class": "58 kg",
        "lifter_name": "Sarah Haggard",
        "lifter_id": 22794,
        "membershipNumbers": [
          {
            "athleteName": "Sarah Haggard",
            "membershipNumber": "1006430",
            "fullText": "1  -  128  Sarah Haggard  F  37  Spoon Barbell Club  1006430  58  2018-03-23  -  Local  Texas-Oklahoma"
          }
        ],
        "sport80Url": "https://usaweightlifting.sport80.com/public/rankings/all?filters=eyJkYXRlX3JhbmdlX3N0YXJ0IjoiMjAxOC0wMy0yMyIsImRhdGVfcmFuZ2VfZW5kIjoiMjAxOC0wMy0yMyIsIndlaWdodF9jbGFzcyI6MzgxfQ=="
      },
      {
        "meet_id": 3353,
        "date": "2018-07-22",
        "age_category": "Women's Masters (35-39)",
        "weight_class": "58 kg",
        "lifter_name": "Sarah Haggard",
        "lifter_id": 22794,
        "membershipNumbers": [
          {
            "athleteName": "Sarah Haggard",
            "membershipNumber": "1006430",
            "fullText": "6  -  120  Sarah Haggard  F  37  Spoon Barbell Club  1006430  57.7  2018-07-22  -  Local  Texas-Oklahoma"
          }
        ],
        "sport80Url": "https://usaweightlifting.sport80.com/public/rankings/all?filters=eyJkYXRlX3JhbmdlX3N0YXJ0IjoiMjAxOC0wNy0yMiIsImRhdGVfcmFuZ2VfZW5kIjoiMjAxOC0wNy0yMiIsIndlaWdodF9jbGFzcyI6MzgxfQ=="
      },
      {
        "meet_id": 3384,
        "date": "2018-07-14",
        "age_category": "Open Women's",
        "weight_class": "69 kg",
        "lifter_name": "Sarah Haggard",
        "lifter_id": 22794,
        "membershipNumbers": [
          {
            "athleteName": "Sarah Haggard",
            "membershipNumber": "1022064",
            "fullText": "12  -  130  Sarah Haggard  F  31  -  1022064  67.8  2018-07-14  -  Local  Pacific Northwest"
          }
        ],
        "sport80Url": "https://usaweightlifting.sport80.com/public/rankings/all?filters=eyJkYXRlX3JhbmdlX3N0YXJ0IjoiMjAxOC0wNy0xNCIsImRhdGVfcmFuZ2VfZW5kIjoiMjAxOC0wNy0xNCIsIndlaWdodF9jbGFzcyI6MzY2fQ=="
      },
      {
        "meet_id": 3454,
        "date": "2018-10-07",
        "age_category": "Women's Masters (35-39)",
        "weight_class": "59kg",
        "lifter_name": "Sarah Haggard",
        "lifter_id": 22794,
        "membershipNumbers": [
          {
            "athleteName": "Sarah Haggard",
            "membershipNumber": "1006430",
            "fullText": "2  -  124  Sarah Haggard  F  37  Spoon Barbell Club  1006430  58.1  2018-10-07  -  Local  Texas-Oklahoma"
          }
        ],
        "sport80Url": "https://usaweightlifting.sport80.com/public/rankings/all?filters=eyJkYXRlX3JhbmdlX3N0YXJ0IjoiMjAxOC0xMC0wNyIsImRhdGVfcmFuZ2VfZW5kIjoiMjAxOC0xMC0wNyIsIndlaWdodF9jbGFzcyI6MTE0fQ=="
      },
      {
        "meet_id": 3854,
        "date": "2019-03-23",
        "age_category": "Open Women's",
        "weight_class": "76kg",
        "lifter_name": "Sarah Haggard",
        "lifter_id": 22794,
        "membershipNumbers": [
          {
            "athleteName": "Sarah Haggard",
            "membershipNumber": "1022064",
            "fullText": "8  -  132  Sarah Haggard  F  32  -  1022064  73  2019-03-23  -  Local  Pacific Northwest"
          }
        ],
        "sport80Url": "https://usaweightlifting.sport80.com/public/rankings/all?filters=eyJkYXRlX3JhbmdlX3N0YXJ0IjoiMjAxOS0wMy0yMyIsImRhdGVfcmFuZ2VfZW5kIjoiMjAxOS0wMy0yMyIsIndlaWdodF9jbGFzcyI6OTd9"
      },
      {
        "meet_id": 2074,
        "date": "2016-08-27",
        "age_category": "Women's Masters (35-39)",
        "weight_class": "58 kg",
        "lifter_name": "Sarah Haggard",
        "lifter_id": 22794,
        "membershipNumbers": [
          {
            "athleteName": "Sarah Haggard",
            "membershipNumber": "1006430",
            "fullText": "7  -  103  Sarah Haggard  F  35  Spoon Barbell Club  1006430  57  2016-08-27  -  Local  Texas-Oklahoma"
          }
        ],
        "sport80Url": "https://usaweightlifting.sport80.com/public/rankings/all?filters=eyJkYXRlX3JhbmdlX3N0YXJ0IjoiMjAxNi0wOC0yNyIsImRhdGVfcmFuZ2VfZW5kIjoiMjAxNi0wOC0yNyIsIndlaWdodF9jbGFzcyI6MzgxfQ=="
      },
      {
        "meet_id": 4564,
        "date": "2020-10-17",
        "age_category": "Women's Masters (35-39)",
        "weight_class": "59kg",
        "lifter_name": "Sarah Haggard",
        "lifter_id": 22794,
        "membershipNumbers": [
          {
            "athleteName": "Sarah Haggard",
            "membershipNumber": "1006430",
            "fullText": "1  -  123  Sarah Haggard  F  39  Spoon Barbell Club  1006430  58.5  2020-10-17  -  Local  Texas-Oklahoma"
          }
        ],
        "sport80Url": "https://usaweightlifting.sport80.com/public/rankings/all?filters=eyJkYXRlX3JhbmdlX3N0YXJ0IjoiMjAyMC0xMC0xNyIsImRhdGVfcmFuZ2VfZW5kIjoiMjAyMC0xMC0xNyIsIndlaWdodF9jbGFzcyI6MTE0fQ=="
      },
      {
        "meet_id": 2766,
        "date": "2017-10-21",
        "age_category": "Open Women's",
        "weight_class": "69 kg",
        "lifter_name": "Sarah Haggard",
        "lifter_id": 22794,
        "membershipNumbers": [],
        "sport80Url": "https://usaweightlifting.sport80.com/public/rankings/all?filters=eyJkYXRlX3JhbmdlX3N0YXJ0IjoiMjAxNy0xMC0yMSIsImRhdGVfcmFuZ2VfZW5kIjoiMjAxNy0xMC0yMSIsIndlaWdodF9jbGFzcyI6MzY2fQ=="
      },
      {
        "meet_id": 4420,
        "date": "2020-01-17",
        "age_category": "Women's Masters (35-39)",
        "weight_class": "59kg",
        "lifter_name": "Sarah Haggard",
        "lifter_id": 22794,
        "membershipNumbers": [
          {
            "athleteName": "Sarah Haggard",
            "membershipNumber": "1006430",
            "fullText": "2  -  114  Sarah Haggard  F  39  Spoon Barbell Club  1006430  58.1  2020-01-17  -  Local  Texas-Oklahoma"
          }
        ],
        "sport80Url": "https://usaweightlifting.sport80.com/public/rankings/all?filters=eyJkYXRlX3JhbmdlX3N0YXJ0IjoiMjAyMC0wMS0xNyIsImRhdGVfcmFuZ2VfZW5kIjoiMjAyMC0wMS0xNyIsIndlaWdodF9jbGFzcyI6MTE0fQ=="
      },
      {
        "meet_id": 2374,
        "date": "2017-04-02",
        "age_category": "Women's Masters (35-39)",
        "weight_class": "58 kg",
        "lifter_name": "Sarah Haggard",
        "lifter_id": 22794,
        "membershipNumbers": [
          {
            "athleteName": "Sarah Haggard",
            "membershipNumber": "1006430",
            "fullText": "1  -  119  Sarah Haggard  F  36  Spoon Barbell Club  1006430  58  2017-04-02  -  Local  Texas-Oklahoma"
          }
        ],
        "sport80Url": "https://usaweightlifting.sport80.com/public/rankings/all?filters=eyJkYXRlX3JhbmdlX3N0YXJ0IjoiMjAxNy0wNC0wMiIsImRhdGVfcmFuZ2VfZW5kIjoiMjAxNy0wNC0wMiIsIndlaWdodF9jbGFzcyI6MzgxfQ=="
      },
      {
        "meet_id": 2891,
        "date": "2018-09-16",
        "age_category": "Open Women's",
        "weight_class": "71kg",
        "lifter_name": "Sarah Haggard",
        "lifter_id": 22794,
        "membershipNumbers": [],
        "sport80Url": "https://usaweightlifting.sport80.com/public/rankings/all?filters=eyJkYXRlX3JhbmdlX3N0YXJ0IjoiMjAxOC0wOS0xNiIsImRhdGVfcmFuZ2VfZW5kIjoiMjAxOC0wOS0xNiIsIndlaWdodF9jbGFzcyI6OTZ9"
      },
      {
        "meet_id": 2967,
        "date": "2018-01-27",
        "age_category": "Open Women's",
        "weight_class": "69 kg",
        "lifter_name": "Sarah Haggard",
        "lifter_id": 22794,
        "membershipNumbers": [
          {
            "athleteName": "Sarah Haggard",
            "membershipNumber": "1022064",
            "fullText": "18  -  119  Sarah Haggard  F  31  -  1022064  68.4  2018-01-27  -  Local  Pacific Northwest"
          }
        ],
        "sport80Url": "https://usaweightlifting.sport80.com/public/rankings/all?filters=eyJkYXRlX3JhbmdlX3N0YXJ0IjoiMjAxOC0wMS0yNyIsImRhdGVfcmFuZ2VfZW5kIjoiMjAxOC0wMS0yNyIsIndlaWdodF9jbGFzcyI6MzY2fQ=="
      },
      {
        "meet_id": 3525,
        "date": "2019-01-20",
        "age_category": "Women's Masters (35-39)",
        "weight_class": "59kg",
        "lifter_name": "Sarah Haggard",
        "lifter_id": 22794,
        "membershipNumbers": [
          {
            "athleteName": "Sarah Haggard",
            "membershipNumber": "1006430",
            "fullText": "1  -  120  Sarah Haggard  F  38  Spoon Barbell Club  1006430  58.01  2019-01-20  -  Local  Texas-Oklahoma"
          }
        ],
        "sport80Url": "https://usaweightlifting.sport80.com/public/rankings/all?filters=eyJkYXRlX3JhbmdlX3N0YXJ0IjoiMjAxOS0wMS0yMCIsImRhdGVfcmFuZ2VfZW5kIjoiMjAxOS0wMS0yMCIsIndlaWdodF9jbGFzcyI6MTE0fQ=="
      },
      {
        "meet_id": 3720,
        "date": "2019-03-31",
        "age_category": "Women's Masters (35-39)",
        "weight_class": "59kg",
        "lifter_name": "Sarah Haggard",
        "lifter_id": 22794,
        "membershipNumbers": [
          {
            "athleteName": "Sarah Haggard",
            "membershipNumber": "1006430",
            "fullText": "11  -  120  Sarah Haggard  F  38  Spoon Barbell Club  1006430  58.8  2019-03-31  -  National  Texas-Oklahoma"
          }
        ],
        "sport80Url": "https://usaweightlifting.sport80.com/public/rankings/all?filters=eyJkYXRlX3JhbmdlX3N0YXJ0IjoiMjAxOS0wMy0zMSIsImRhdGVfcmFuZ2VfZW5kIjoiMjAxOS0wMy0zMSIsIndlaWdodF9jbGFzcyI6MTE0fQ=="
      },
      {
        "meet_id": 4178,
        "date": "2019-10-13",
        "age_category": "Women's Masters (35-39)",
        "weight_class": "59kg",
        "lifter_name": "Sarah Haggard",
        "lifter_id": 22794,
        "membershipNumbers": [
          {
            "athleteName": "Sarah Haggard",
            "membershipNumber": "1006430",
            "fullText": "1  -  111  Sarah Haggard  F  38  Spoon Barbell Club  1006430  58.28  2019-10-13  -  Local  Texas-Oklahoma"
          }
        ],
        "sport80Url": "https://usaweightlifting.sport80.com/public/rankings/all?filters=eyJkYXRlX3JhbmdlX3N0YXJ0IjoiMjAxOS0xMC0xMyIsImRhdGVfcmFuZ2VfZW5kIjoiMjAxOS0xMC0xMyIsIndlaWdodF9jbGFzcyI6MTE0fQ=="
      },
      {
        "meet_id": 5863,
        "date": "2023-05-13",
        "age_category": "Women's Masters (35-39)",
        "weight_class": "76kg",
        "lifter_name": "Sarah Haggard",
        "lifter_id": 22794,
        "membershipNumbers": [
          {
            "athleteName": "Sarah Haggard",
            "membershipNumber": "1022064",
            "fullText": "4  -  119  Sarah Haggard  F  36  -  1022064  74.8  2023-05-13  -  Local  Pacific Northwest"
          }
        ],
        "sport80Url": "https://usaweightlifting.sport80.com/public/rankings/all?filters=eyJkYXRlX3JhbmdlX3N0YXJ0IjoiMjAyMy0wNS0xMyIsImRhdGVfcmFuZ2VfZW5kIjoiMjAyMy0wNS0xMyIsIndlaWdodF9jbGFzcyI6MTE3fQ=="
      },
      {
        "meet_id": 4543,
        "date": "2020-08-08",
        "age_category": "Women's Masters (35-39)",
        "weight_class": "59kg",
        "lifter_name": "Sarah Haggard",
        "lifter_id": 22794,
        "membershipNumbers": [
          {
            "athleteName": "Sarah Haggard",
            "membershipNumber": "1006430",
            "fullText": "1  -  120  Sarah Haggard  F  39  Spoon Barbell Club  1006430  58.5  2020-08-08  -  Local  Texas-Oklahoma"
          }
        ],
        "sport80Url": "https://usaweightlifting.sport80.com/public/rankings/all?filters=eyJkYXRlX3JhbmdlX3N0YXJ0IjoiMjAyMC0wOC0wOCIsImRhdGVfcmFuZ2VfZW5kIjoiMjAyMC0wOC0wOCIsIndlaWdodF9jbGFzcyI6MTE0fQ=="
      }
    ],
    "analysis": {
      "distinctAthletes": 2,
      "membershipGroups": {
        "1006430": [
          {
            "meet_id": 4725,
            "date": "2021-01-15",
            "age_category": "Women's Masters (40-44)",
            "weight_class": "59kg",
            "lifter_name": "Sarah Haggard",
            "lifter_id": 22794,
            "membershipNumbers": [
              {
                "athleteName": "Sarah Haggard",
                "membershipNumber": "1006430",
                "fullText": "2  -  116  Sarah Haggard  F  40  Spoon Barbell Club  1006430  58.7  2021-01-15  -  Local  Texas-Oklahoma"
              }
            ],
            "sport80Url": "https://usaweightlifting.sport80.com/public/rankings/all?filters=eyJkYXRlX3JhbmdlX3N0YXJ0IjoiMjAyMS0wMS0xNSIsImRhdGVfcmFuZ2VfZW5kIjoiMjAyMS0wMS0xNSIsIndlaWdodF9jbGFzcyI6MTM0fQ=="
          },
          {
            "meet_id": 4817,
            "date": "2021-02-27",
            "age_category": "Women's Masters (40-44)",
            "weight_class": "59kg",
            "lifter_name": "Sarah Haggard",
            "lifter_id": 22794,
            "membershipNumbers": [
              {
                "athleteName": "Sarah Haggard",
                "membershipNumber": "1006430",
                "fullText": "1  -  112  Sarah Haggard  F  40  Spoon Barbell Club  1006430  58.71  2021-02-27  -  Local  Texas-Oklahoma"
              }
            ],
            "sport80Url": "https://usaweightlifting.sport80.com/public/rankings/all?filters=eyJkYXRlX3JhbmdlX3N0YXJ0IjoiMjAyMS0wMi0yNyIsImRhdGVfcmFuZ2VfZW5kIjoiMjAyMS0wMi0yNyIsIndlaWdodF9jbGFzcyI6MTM0fQ=="
          },
          {
            "meet_id": 4867,
            "date": "2021-05-08",
            "age_category": "Women's Masters (40-44)",
            "weight_class": "64kg",
            "lifter_name": "Sarah Haggard",
            "lifter_id": 22794,
            "membershipNumbers": [
              {
                "athleteName": "Sarah Haggard",
                "membershipNumber": "1006430",
                "fullText": "5  -  120  Sarah Haggard  F  40  Spoon Barbell Club  1006430  59.9  2021-05-08  -  Local  Texas-Oklahoma"
              }
            ],
            "sport80Url": "https://usaweightlifting.sport80.com/public/rankings/all?filters=eyJkYXRlX3JhbmdlX3N0YXJ0IjoiMjAyMS0wNS0wOCIsImRhdGVfcmFuZ2VfZW5kIjoiMjAyMS0wNS0wOCIsIndlaWdodF9jbGFzcyI6MTM1fQ=="
          },
          {
            "meet_id": 5331,
            "date": "2022-05-14",
            "age_category": "Women's Masters (40-44)",
            "weight_class": "59kg",
            "lifter_name": "Sarah Haggard",
            "lifter_id": 22794,
            "membershipNumbers": [
              {
                "athleteName": "Sarah Haggard",
                "membershipNumber": "1006430",
                "fullText": "2  -  108  Sarah Haggard  F  41  Spoon Barbell Club  1006430  58.91  2022-05-14  -  Local  Texas-Oklahoma"
              }
            ],
            "sport80Url": "https://usaweightlifting.sport80.com/public/rankings/all?filters=eyJkYXRlX3JhbmdlX3N0YXJ0IjoiMjAyMi0wNS0xNCIsImRhdGVfcmFuZ2VfZW5kIjoiMjAyMi0wNS0xNCIsIndlaWdodF9jbGFzcyI6MTM0fQ=="
          },
          {
            "meet_id": 1766,
            "date": "2016-07-09",
            "age_category": "Women's Masters (35-39)",
            "weight_class": "58 kg",
            "lifter_name": "Sarah Haggard",
            "lifter_id": 22794,
            "membershipNumbers": [
              {
                "athleteName": "Sarah Haggard",
                "membershipNumber": "1006430",
                "fullText": "6  -  92  Sarah Haggard  F  35  Spoon Barbell Club  1006430  57.1  2016-07-09  -  Local  Texas-Oklahoma"
              }
            ],
            "sport80Url": "https://usaweightlifting.sport80.com/public/rankings/all?filters=eyJkYXRlX3JhbmdlX3N0YXJ0IjoiMjAxNi0wNy0wOSIsImRhdGVfcmFuZ2VfZW5kIjoiMjAxNi0wNy0wOSIsIndlaWdodF9jbGFzcyI6MzgxfQ=="
          },
          {
            "meet_id": 2217,
            "date": "2016-10-16",
            "age_category": "Women's Masters (35-39)",
            "weight_class": "58 kg",
            "lifter_name": "Sarah Haggard",
            "lifter_id": 22794,
            "membershipNumbers": [
              {
                "athleteName": "Sarah Haggard",
                "membershipNumber": "1006430",
                "fullText": "4  -  109  Sarah Haggard  F  35  Spoon Barbell Club  1006430  56.95  2016-10-16  -  Local  Texas-Oklahoma"
              }
            ],
            "sport80Url": "https://usaweightlifting.sport80.com/public/rankings/all?filters=eyJkYXRlX3JhbmdlX3N0YXJ0IjoiMjAxNi0xMC0xNiIsImRhdGVfcmFuZ2VfZW5kIjoiMjAxNi0xMC0xNiIsIndlaWdodF9jbGFzcyI6MzgxfQ=="
          },
          {
            "meet_id": 2356,
            "date": "2017-01-15",
            "age_category": "Women's Masters (35-39)",
            "weight_class": "58 kg",
            "lifter_name": "Sarah Haggard",
            "lifter_id": 22794,
            "membershipNumbers": [
              {
                "athleteName": "Sarah Haggard",
                "membershipNumber": "1006430",
                "fullText": "6  -  108  Sarah Haggard  F  36  Spoon Barbell Club  1006430  56.8  2017-01-15  -  Local  Texas-Oklahoma"
              }
            ],
            "sport80Url": "https://usaweightlifting.sport80.com/public/rankings/all?filters=eyJkYXRlX3JhbmdlX3N0YXJ0IjoiMjAxNy0wMS0xNSIsImRhdGVfcmFuZ2VfZW5kIjoiMjAxNy0wMS0xNSIsIndlaWdodF9jbGFzcyI6MzgxfQ=="
          },
          {
            "meet_id": 2622,
            "date": "2017-05-21",
            "age_category": "Women's Masters (35-39)",
            "weight_class": "58 kg",
            "lifter_name": "Sarah Haggard",
            "lifter_id": 22794,
            "membershipNumbers": [
              {
                "athleteName": "Sarah Haggard",
                "membershipNumber": "1006430",
                "fullText": "2  -  119  Sarah Haggard  F  36  Spoon Barbell Club  1006430  57.3  2017-05-21  -  Local  Texas-Oklahoma"
              }
            ],
            "sport80Url": "https://usaweightlifting.sport80.com/public/rankings/all?filters=eyJkYXRlX3JhbmdlX3N0YXJ0IjoiMjAxNy0wNS0yMSIsImRhdGVfcmFuZ2VfZW5kIjoiMjAxNy0wNS0yMSIsIndlaWdodF9jbGFzcyI6MzgxfQ=="
          },
          {
            "meet_id": 2780,
            "date": "2017-10-29",
            "age_category": "Women's Masters (35-39)",
            "weight_class": "63 kg",
            "lifter_name": "Sarah Haggard",
            "lifter_id": 22794,
            "membershipNumbers": [
              {
                "athleteName": "Sarah Haggard",
                "membershipNumber": "1006430",
                "fullText": "6  -  119  Sarah Haggard  F  36  Spoon Barbell Club  1006430  58.2  2017-10-29  -  Local  Texas-Oklahoma"
              }
            ],
            "sport80Url": "https://usaweightlifting.sport80.com/public/rankings/all?filters=eyJkYXRlX3JhbmdlX3N0YXJ0IjoiMjAxNy0xMC0yOSIsImRhdGVfcmFuZ2VfZW5kIjoiMjAxNy0xMC0yOSIsIndlaWdodF9jbGFzcyI6MzgyfQ=="
          },
          {
            "meet_id": 2802,
            "date": "2017-10-15",
            "age_category": "Women's Masters (35-39)",
            "weight_class": "58 kg",
            "lifter_name": "Sarah Haggard",
            "lifter_id": 22794,
            "membershipNumbers": [
              {
                "athleteName": "Sarah Haggard",
                "membershipNumber": "1006430",
                "fullText": "4  -  119  Sarah Haggard  F  36  Spoon Barbell Club  1006430  57.92  2017-10-15  -  Local  Texas-Oklahoma"
              }
            ],
            "sport80Url": "https://usaweightlifting.sport80.com/public/rankings/all?filters=eyJkYXRlX3JhbmdlX3N0YXJ0IjoiMjAxNy0xMC0xNSIsImRhdGVfcmFuZ2VfZW5kIjoiMjAxNy0xMC0xNSIsIndlaWdodF9jbGFzcyI6MzgxfQ=="
          },
          {
            "meet_id": 2939,
            "date": "2018-01-14",
            "age_category": "Women's Masters (35-39)",
            "weight_class": "58 kg",
            "lifter_name": "Sarah Haggard",
            "lifter_id": 22794,
            "membershipNumbers": [
              {
                "athleteName": "Sarah Haggard",
                "membershipNumber": "1006430",
                "fullText": "5  -  125  Sarah Haggard  F  37  Spoon Barbell Club  1006430  58  2018-01-14  -  Local  Texas-Oklahoma"
              }
            ],
            "sport80Url": "https://usaweightlifting.sport80.com/public/rankings/all?filters=eyJkYXRlX3JhbmdlX3N0YXJ0IjoiMjAxOC0wMS0xNCIsImRhdGVfcmFuZ2VfZW5kIjoiMjAxOC0wMS0xNCIsIndlaWdodF9jbGFzcyI6MzgxfQ=="
          },
          {
            "meet_id": 3072,
            "date": "2018-03-31",
            "age_category": "Women's Masters (35-39)",
            "weight_class": "58 kg",
            "lifter_name": "Sarah Haggard",
            "lifter_id": 22794,
            "membershipNumbers": [
              {
                "athleteName": "Sarah Haggard",
                "membershipNumber": "1006430",
                "fullText": "1  -  128  Sarah Haggard  F  37  Spoon Barbell Club  1006430  57.9  2018-03-31  -  Local  Texas-Oklahoma"
              }
            ],
            "sport80Url": "https://usaweightlifting.sport80.com/public/rankings/all?filters=eyJkYXRlX3JhbmdlX3N0YXJ0IjoiMjAxOC0wMy0zMSIsImRhdGVfcmFuZ2VfZW5kIjoiMjAxOC0wMy0zMSIsIndlaWdodF9jbGFzcyI6MzgxfQ=="
          },
          {
            "meet_id": 3180,
            "date": "2018-05-06",
            "age_category": "Women's Masters (35-39)",
            "weight_class": "58 kg",
            "lifter_name": "Sarah Haggard",
            "lifter_id": 22794,
            "membershipNumbers": [
              {
                "athleteName": "Sarah Haggard",
                "membershipNumber": "1006430",
                "fullText": "1  -  129  Sarah Haggard  F  37  Spoon Barbell Club  1006430  57.99  2018-05-06  -  Local  Texas-Oklahoma"
              }
            ],
            "sport80Url": "https://usaweightlifting.sport80.com/public/rankings/all?filters=eyJkYXRlX3JhbmdlX3N0YXJ0IjoiMjAxOC0wNS0wNiIsImRhdGVfcmFuZ2VfZW5kIjoiMjAxOC0wNS0wNiIsIndlaWdodF9jbGFzcyI6MzgxfQ=="
          },
          {
            "meet_id": 3276,
            "date": "2018-03-23",
            "age_category": "Women's Masters (35-39)",
            "weight_class": "58 kg",
            "lifter_name": "Sarah Haggard",
            "lifter_id": 22794,
            "membershipNumbers": [
              {
                "athleteName": "Sarah Haggard",
                "membershipNumber": "1006430",
                "fullText": "1  -  128  Sarah Haggard  F  37  Spoon Barbell Club  1006430  58  2018-03-23  -  Local  Texas-Oklahoma"
              }
            ],
            "sport80Url": "https://usaweightlifting.sport80.com/public/rankings/all?filters=eyJkYXRlX3JhbmdlX3N0YXJ0IjoiMjAxOC0wMy0yMyIsImRhdGVfcmFuZ2VfZW5kIjoiMjAxOC0wMy0yMyIsIndlaWdodF9jbGFzcyI6MzgxfQ=="
          },
          {
            "meet_id": 3353,
            "date": "2018-07-22",
            "age_category": "Women's Masters (35-39)",
            "weight_class": "58 kg",
            "lifter_name": "Sarah Haggard",
            "lifter_id": 22794,
            "membershipNumbers": [
              {
                "athleteName": "Sarah Haggard",
                "membershipNumber": "1006430",
                "fullText": "6  -  120  Sarah Haggard  F  37  Spoon Barbell Club  1006430  57.7  2018-07-22  -  Local  Texas-Oklahoma"
              }
            ],
            "sport80Url": "https://usaweightlifting.sport80.com/public/rankings/all?filters=eyJkYXRlX3JhbmdlX3N0YXJ0IjoiMjAxOC0wNy0yMiIsImRhdGVfcmFuZ2VfZW5kIjoiMjAxOC0wNy0yMiIsIndlaWdodF9jbGFzcyI6MzgxfQ=="
          },
          {
            "meet_id": 3454,
            "date": "2018-10-07",
            "age_category": "Women's Masters (35-39)",
            "weight_class": "59kg",
            "lifter_name": "Sarah Haggard",
            "lifter_id": 22794,
            "membershipNumbers": [
              {
                "athleteName": "Sarah Haggard",
                "membershipNumber": "1006430",
                "fullText": "2  -  124  Sarah Haggard  F  37  Spoon Barbell Club  1006430  58.1  2018-10-07  -  Local  Texas-Oklahoma"
              }
            ],
            "sport80Url": "https://usaweightlifting.sport80.com/public/rankings/all?filters=eyJkYXRlX3JhbmdlX3N0YXJ0IjoiMjAxOC0xMC0wNyIsImRhdGVfcmFuZ2VfZW5kIjoiMjAxOC0xMC0wNyIsIndlaWdodF9jbGFzcyI6MTE0fQ=="
          },
          {
            "meet_id": 2074,
            "date": "2016-08-27",
            "age_category": "Women's Masters (35-39)",
            "weight_class": "58 kg",
            "lifter_name": "Sarah Haggard",
            "lifter_id": 22794,
            "membershipNumbers": [
              {
                "athleteName": "Sarah Haggard",
                "membershipNumber": "1006430",
                "fullText": "7  -  103  Sarah Haggard  F  35  Spoon Barbell Club  1006430  57  2016-08-27  -  Local  Texas-Oklahoma"
              }
            ],
            "sport80Url": "https://usaweightlifting.sport80.com/public/rankings/all?filters=eyJkYXRlX3JhbmdlX3N0YXJ0IjoiMjAxNi0wOC0yNyIsImRhdGVfcmFuZ2VfZW5kIjoiMjAxNi0wOC0yNyIsIndlaWdodF9jbGFzcyI6MzgxfQ=="
          },
          {
            "meet_id": 4564,
            "date": "2020-10-17",
            "age_category": "Women's Masters (35-39)",
            "weight_class": "59kg",
            "lifter_name": "Sarah Haggard",
            "lifter_id": 22794,
            "membershipNumbers": [
              {
                "athleteName": "Sarah Haggard",
                "membershipNumber": "1006430",
                "fullText": "1  -  123  Sarah Haggard  F  39  Spoon Barbell Club  1006430  58.5  2020-10-17  -  Local  Texas-Oklahoma"
              }
            ],
            "sport80Url": "https://usaweightlifting.sport80.com/public/rankings/all?filters=eyJkYXRlX3JhbmdlX3N0YXJ0IjoiMjAyMC0xMC0xNyIsImRhdGVfcmFuZ2VfZW5kIjoiMjAyMC0xMC0xNyIsIndlaWdodF9jbGFzcyI6MTE0fQ=="
          },
          {
            "meet_id": 4420,
            "date": "2020-01-17",
            "age_category": "Women's Masters (35-39)",
            "weight_class": "59kg",
            "lifter_name": "Sarah Haggard",
            "lifter_id": 22794,
            "membershipNumbers": [
              {
                "athleteName": "Sarah Haggard",
                "membershipNumber": "1006430",
                "fullText": "2  -  114  Sarah Haggard  F  39  Spoon Barbell Club  1006430  58.1  2020-01-17  -  Local  Texas-Oklahoma"
              }
            ],
            "sport80Url": "https://usaweightlifting.sport80.com/public/rankings/all?filters=eyJkYXRlX3JhbmdlX3N0YXJ0IjoiMjAyMC0wMS0xNyIsImRhdGVfcmFuZ2VfZW5kIjoiMjAyMC0wMS0xNyIsIndlaWdodF9jbGFzcyI6MTE0fQ=="
          },
          {
            "meet_id": 2374,
            "date": "2017-04-02",
            "age_category": "Women's Masters (35-39)",
            "weight_class": "58 kg",
            "lifter_name": "Sarah Haggard",
            "lifter_id": 22794,
            "membershipNumbers": [
              {
                "athleteName": "Sarah Haggard",
                "membershipNumber": "1006430",
                "fullText": "1  -  119  Sarah Haggard  F  36  Spoon Barbell Club  1006430  58  2017-04-02  -  Local  Texas-Oklahoma"
              }
            ],
            "sport80Url": "https://usaweightlifting.sport80.com/public/rankings/all?filters=eyJkYXRlX3JhbmdlX3N0YXJ0IjoiMjAxNy0wNC0wMiIsImRhdGVfcmFuZ2VfZW5kIjoiMjAxNy0wNC0wMiIsIndlaWdodF9jbGFzcyI6MzgxfQ=="
          },
          {
            "meet_id": 3525,
            "date": "2019-01-20",
            "age_category": "Women's Masters (35-39)",
            "weight_class": "59kg",
            "lifter_name": "Sarah Haggard",
            "lifter_id": 22794,
            "membershipNumbers": [
              {
                "athleteName": "Sarah Haggard",
                "membershipNumber": "1006430",
                "fullText": "1  -  120  Sarah Haggard  F  38  Spoon Barbell Club  1006430  58.01  2019-01-20  -  Local  Texas-Oklahoma"
              }
            ],
            "sport80Url": "https://usaweightlifting.sport80.com/public/rankings/all?filters=eyJkYXRlX3JhbmdlX3N0YXJ0IjoiMjAxOS0wMS0yMCIsImRhdGVfcmFuZ2VfZW5kIjoiMjAxOS0wMS0yMCIsIndlaWdodF9jbGFzcyI6MTE0fQ=="
          },
          {
            "meet_id": 3720,
            "date": "2019-03-31",
            "age_category": "Women's Masters (35-39)",
            "weight_class": "59kg",
            "lifter_name": "Sarah Haggard",
            "lifter_id": 22794,
            "membershipNumbers": [
              {
                "athleteName": "Sarah Haggard",
                "membershipNumber": "1006430",
                "fullText": "11  -  120  Sarah Haggard  F  38  Spoon Barbell Club  1006430  58.8  2019-03-31  -  National  Texas-Oklahoma"
              }
            ],
            "sport80Url": "https://usaweightlifting.sport80.com/public/rankings/all?filters=eyJkYXRlX3JhbmdlX3N0YXJ0IjoiMjAxOS0wMy0zMSIsImRhdGVfcmFuZ2VfZW5kIjoiMjAxOS0wMy0zMSIsIndlaWdodF9jbGFzcyI6MTE0fQ=="
          },
          {
            "meet_id": 4178,
            "date": "2019-10-13",
            "age_category": "Women's Masters (35-39)",
            "weight_class": "59kg",
            "lifter_name": "Sarah Haggard",
            "lifter_id": 22794,
            "membershipNumbers": [
              {
                "athleteName": "Sarah Haggard",
                "membershipNumber": "1006430",
                "fullText": "1  -  111  Sarah Haggard  F  38  Spoon Barbell Club  1006430  58.28  2019-10-13  -  Local  Texas-Oklahoma"
              }
            ],
            "sport80Url": "https://usaweightlifting.sport80.com/public/rankings/all?filters=eyJkYXRlX3JhbmdlX3N0YXJ0IjoiMjAxOS0xMC0xMyIsImRhdGVfcmFuZ2VfZW5kIjoiMjAxOS0xMC0xMyIsIndlaWdodF9jbGFzcyI6MTE0fQ=="
          },
          {
            "meet_id": 4543,
            "date": "2020-08-08",
            "age_category": "Women's Masters (35-39)",
            "weight_class": "59kg",
            "lifter_name": "Sarah Haggard",
            "lifter_id": 22794,
            "membershipNumbers": [
              {
                "athleteName": "Sarah Haggard",
                "membershipNumber": "1006430",
                "fullText": "1  -  120  Sarah Haggard  F  39  Spoon Barbell Club  1006430  58.5  2020-08-08  -  Local  Texas-Oklahoma"
              }
            ],
            "sport80Url": "https://usaweightlifting.sport80.com/public/rankings/all?filters=eyJkYXRlX3JhbmdlX3N0YXJ0IjoiMjAyMC0wOC0wOCIsImRhdGVfcmFuZ2VfZW5kIjoiMjAyMC0wOC0wOCIsIndlaWdodF9jbGFzcyI6MTE0fQ=="
          }
        ],
        "1022064": [
          {
            "meet_id": 3384,
            "date": "2018-07-14",
            "age_category": "Open Women's",
            "weight_class": "69 kg",
            "lifter_name": "Sarah Haggard",
            "lifter_id": 22794,
            "membershipNumbers": [
              {
                "athleteName": "Sarah Haggard",
                "membershipNumber": "1022064",
                "fullText": "12  -  130  Sarah Haggard  F  31  -  1022064  67.8  2018-07-14  -  Local  Pacific Northwest"
              }
            ],
            "sport80Url": "https://usaweightlifting.sport80.com/public/rankings/all?filters=eyJkYXRlX3JhbmdlX3N0YXJ0IjoiMjAxOC0wNy0xNCIsImRhdGVfcmFuZ2VfZW5kIjoiMjAxOC0wNy0xNCIsIndlaWdodF9jbGFzcyI6MzY2fQ=="
          },
          {
            "meet_id": 3854,
            "date": "2019-03-23",
            "age_category": "Open Women's",
            "weight_class": "76kg",
            "lifter_name": "Sarah Haggard",
            "lifter_id": 22794,
            "membershipNumbers": [
              {
                "athleteName": "Sarah Haggard",
                "membershipNumber": "1022064",
                "fullText": "8  -  132  Sarah Haggard  F  32  -  1022064  73  2019-03-23  -  Local  Pacific Northwest"
              }
            ],
            "sport80Url": "https://usaweightlifting.sport80.com/public/rankings/all?filters=eyJkYXRlX3JhbmdlX3N0YXJ0IjoiMjAxOS0wMy0yMyIsImRhdGVfcmFuZ2VfZW5kIjoiMjAxOS0wMy0yMyIsIndlaWdodF9jbGFzcyI6OTd9"
          },
          {
            "meet_id": 2967,
            "date": "2018-01-27",
            "age_category": "Open Women's",
            "weight_class": "69 kg",
            "lifter_name": "Sarah Haggard",
            "lifter_id": 22794,
            "membershipNumbers": [
              {
                "athleteName": "Sarah Haggard",
                "membershipNumber": "1022064",
                "fullText": "18  -  119  Sarah Haggard  F  31  -  1022064  68.4  2018-01-27  -  Local  Pacific Northwest"
              }
            ],
            "sport80Url": "https://usaweightlifting.sport80.com/public/rankings/all?filters=eyJkYXRlX3JhbmdlX3N0YXJ0IjoiMjAxOC0wMS0yNyIsImRhdGVfcmFuZ2VfZW5kIjoiMjAxOC0wMS0yNyIsIndlaWdodF9jbGFzcyI6MzY2fQ=="
          },
          {
            "meet_id": 5863,
            "date": "2023-05-13",
            "age_category": "Women's Masters (35-39)",
            "weight_class": "76kg",
            "lifter_name": "Sarah Haggard",
            "lifter_id": 22794,
            "membershipNumbers": [
              {
                "athleteName": "Sarah Haggard",
                "membershipNumber": "1022064",
                "fullText": "4  -  119  Sarah Haggard  F  36  -  1022064  74.8  2023-05-13  -  Local  Pacific Northwest"
              }
            ],
            "sport80Url": "https://usaweightlifting.sport80.com/public/rankings/all?filters=eyJkYXRlX3JhbmdlX3N0YXJ0IjoiMjAyMy0wNS0xMyIsImRhdGVfcmFuZ2VfZW5kIjoiMjAyMy0wNS0xMyIsIndlaWdodF9jbGFzcyI6MTE3fQ=="
          }
        ]
      },
      "unidentifiedCompetitions": [
        {
          "meet_id": 2766,
          "date": "2017-10-21",
          "age_category": "Open Women's",
          "weight_class": "69 kg",
          "lifter_name": "Sarah Haggard",
          "lifter_id": 22794,
          "membershipNumbers": [],
          "sport80Url": "https://usaweightlifting.sport80.com/public/rankings/all?filters=eyJkYXRlX3JhbmdlX3N0YXJ0IjoiMjAxNy0xMC0yMSIsImRhdGVfcmFuZ2VfZW5kIjoiMjAxNy0xMC0yMSIsIndlaWdodF9jbGFzcyI6MzY2fQ=="
        },
        {
          "meet_id": 2891,
          "date": "2018-09-16",
          "age_category": "Open Women's",
          "weight_class": "71kg",
          "lifter_name": "Sarah Haggard",
          "lifter_id": 22794,
          "membershipNumbers": [],
          "sport80Url": "https://usaweightlifting.sport80.com/public/rankings/all?filters=eyJkYXRlX3JhbmdlX3N0YXJ0IjoiMjAxOC0wOS0xNiIsImRhdGVfcmFuZ2VfZW5kIjoiMjAxOC0wOS0xNiIsIndlaWdodF9jbGFzcyI6OTZ9"
        }
      ],
      "splitRequired": true
    }
  }
}